{
  "_board_id_user_set_migrated": true,
  "_dashboard_identity": {
    "dashboard_id": "mYCVv5NS_1U9dRc0lnM2Vh42k5IXInL-"
  },
  "proxy_sleep.yaml": {
    "mac_address": "D4:D4:DA:84:2C:F4"
  },
  "proxy_kitchen.yaml": {
    "mac_address": "D4:D4:DA:84:28:28"
  },
  "proxy_hallway.yaml": {
    "mac_address": "64:B7:08:A0:B8:3C"
  },
  "proxy_couch.yaml": {
    "mac_address": "D4:D4:DA:9F:02:FC"
  },
  "proxy_office.yaml": {
    "mac_address": "64:B7:08:A0:5B:E4"
  },
  "_firmware_jobs": [
    {
      "job_id": "951ed867c187",
      "configuration": "proxy_hallway.yaml",
      "job_type": "upload",
      "status": "completed",
      "created_at": "2026-07-09T21:50:14.841569+00:00",
      "started_at": "2026-07-09T21:50:14.841686+00:00",
      "completed_at": "2026-07-09T21:50:28.898315+00:00",
      "exit_code": 0,
      "error": null,
      "port": "OTA",
      "flash_bootloader": false,
      "is_deferred_install": false,
      "new_name": "",
      "depends_on": "",
      "dependency_released": false,
      "progress": 100,
      "remote_peer": "",
      "remote_job_id": "",
      "remote_peer_label": "",
      "device_name": "",
      "device_friendly_name": "",
      "source": "local",
      "source_pin_sha256": "",
      "source_label": "",
      "source_esphome_version": "",
      "target_esphome_version": "",
      "failure_reason": ""
    },
    {
      "job_id": "23f9ee3a1627",
      "configuration": "proxy_hallway.yaml",
      "job_type": "compile",
      "status": "completed",
      "created_at": "2026-07-09T21:47:56.262116+00:00",
      "started_at": "2026-07-09T21:47:56.328681+00:00",
      "completed_at": "2026-07-09T21:50:14.839262+00:00",
      "exit_code": 0,
      "error": null,
      "port": "",
      "flash_bootloader": false,
      "is_deferred_install": false,
      "new_name": "",
      "depends_on": "",
      "dependency_released": false,
      "progress": null,
      "remote_peer": "",
      "remote_job_id": "",
      "remote_peer_label": "",
      "device_name": "",
      "device_friendly_name": "",
      "source": "local",
      "source_pin_sha256": "",
      "source_label": "",
      "source_esphome_version": "",
      "target_esphome_version": "",
      "failure_reason": ""
    },
    {
      "job_id": "f02d2025b004",
      "configuration": "s3box_main.yaml",
      "job_type": "upload",
      "status": "completed",
      "created_at": "2026-07-09T21:47:56.261539+00:00",
      "started_at": "2026-07-09T21:47:56.261654+00:00",
      "completed_at": "2026-07-09T21:48:21.802470+00:00",
      "exit_code": 0,
      "error": null,
      "port": "OTA",
      "flash_bootloader": false,
      "is_deferred_install": false,
      "new_name": "",
      "depends_on": "",
      "dependency_released": false,
      "progress": 100,
      "remote_peer": "",
      "remote_job_id": "",
      "remote_peer_label": "",
      "device_name": "",
      "device_friendly_name": "",
      "source": "local",
      "source_pin_sha256": "",
      "source_label": "",
      "source_esphome_version": "",
      "target_esphome_version": "",
      "failure_reason": ""
    },
    {
      "job_id": "aa7cc6cf27ab",
      "configuration": "proxy_office.yaml",
      "job_type": "upload",
      "status": "completed",
      "created_at": "2026-07-09T21:42:04.377997+00:00",
      "started_at": "2026-07-09T21:42:04.378083+00:00",
      "completed_at": "2026-07-09T21:42:18.950064+00:00",
      "exit_code": 0,
      "error": null,
      "port": "OTA",
      "flash_bootloader": false,
      "is_deferred_install": false,
      "new_name": "",
      "depends_on": "",
      "dependency_released": false,
      "progress": 100,
      "remote_peer": "",
      "remote_job_id": "",
      "remote_peer_label": "",
      "device_name": "",
      "device_friendly_name": "",
      "source": "local",
      "source_pin_sha256": "",
      "source_label": "",
      "source_esphome_version": "",
      "target_esphome_version": "",
      "failure_reason": ""
    },
    {
      "job_id": "547236ab4241",
      "configuration": "s3box_main.yaml",
      "job_type": "compile",
      "status": "completed",
      "created_at": "2026-07-09T21:42:04.377926+00:00",
      "started_at": "2026-07-09T21:42:04.378735+00:00",
      "completed_at": "2026-07-09T21:47:56.257845+00:00",
      "exit_code": 0,
      "error": null,
      "port": "",
      "flash_bootloader": false,
      "is_deferred_install": false,
      "new_name": "",
      "depends_on": "",
      "dependency_released": false,
      "progress": null,
      "remote_peer": "",
      "remote_job_id": "",
      "remote_peer_label": "",
      "device_name": "",
      "device_friendly_name": "",
      "source": "local",
      "source_pin_sha256": "",
      "source_label": "",
      "source_esphome_version": "",
      "target_esphome_version": "",
      "failure_reason": ""
    },
    {
      "job_id": "939fe00a819d",
      "configuration": "proxy_office.yaml",
      "job_type": "compile",
      "status": "completed",
      "created_at": "2026-07-09T21:39:49.267166+00:00",
      "started_at": "2026-07-09T21:39:49.272208+00:00",
      "completed_at": "2026-07-09T21:42:04.374841+00:00",
      "exit_code": 0,
      "error": null,
      "port": "",
      "flash_bootloader": false,
      "is_deferred_install": false,
      "new_name": "",
      "depends_on": "",
      "dependency_released": false,
      "progress": null,
      "remote_peer": "",
      "remote_job_id": "",
      "remote_peer_label": "",
      "device_name": "",
      "device_friendly_name": "",
      "source": "local",
      "source_pin_sha256": "",
      "source_label": "",
      "source_esphome_version": "",
      "target_esphome_version": "",
      "failure_reason": ""
    },
    {
      "job_id": "bf86fa3bb89b",
      "configuration": "proxy_couch.yaml",
      "job_type": "upload",
      "status": "completed",
      "created_at": "2026-07-09T21:39:49.266641+00:00",
      "started_at": "2026-07-09T21:39:49.266755+00:00",
      "completed_at": "2026-07-09T21:40:03.801246+00:00",
      "exit_code": 0,
      "error": null,
      "port": "OTA",
      "flash_bootloader": false,
      "is_deferred_install": false,
      "new_name": "",
      "depends_on": "",
      "dependency_released": false,
      "progress": 100,
      "remote_peer": "",
      "remote_job_id": "",
      "remote_peer_label": "",
      "device_name": "",
      "device_friendly_name": "",
      "source": "local",
      "source_pin_sha256": "",
      "source_label": "",
      "source_esphome_version": "",
      "target_esphome_version": "",
      "failure_reason": ""
    },
    {
      "job_id": "a0a527354d57",
      "configuration": "proxy_sleep.yaml",
      "job_type": "upload",
      "status": "completed",
      "created_at": "2026-07-09T21:37:35.653091+00:00",
      "started_at": "2026-07-09T21:37:35.653286+00:00",
      "completed_at": "2026-07-09T21:37:57.035114+00:00",
      "exit_code": 0,
      "error": null,
      "port": "OTA",
      "flash_bootloader": false,
      "is_deferred_install": false,
      "new_name": "",
      "depends_on": "",
      "dependency_released": false,
      "progress": 100,
      "remote_peer": "",
      "remote_job_id": "",
      "remote_peer_label": "",
      "device_name": "",
      "device_friendly_name": "",
      "source": "local",
      "source_pin_sha256": "",
      "source_label": "",
      "source_esphome_version": "",
      "target_esphome_version": "",
      "failure_reason": ""
    },
    {
      "job_id": "903c46297630",
      "configuration": "proxy_couch.yaml",
      "job_type": "compile",
      "status": "completed",
      "created_at": "2026-07-09T21:37:35.652383+00:00",
      "started_at": "2026-07-09T21:37:35.653233+00:00",
      "completed_at": "2026-07-09T21:39:49.264323+00:00",
      "exit_code": 0,
      "error": null,
      "port": "",
      "flash_bootloader": false,
      "is_deferred_install": false,
      "new_name": "",
      "depends_on": "",
      "dependency_released": false,
      "progress": null,
      "remote_peer": "",
      "remote_job_id": "",
      "remote_peer_label": "",
      "device_name": "",
      "device_friendly_name": "",
      "source": "local",
      "source_pin_sha256": "",
      "source_label": "",
      "source_esphome_version": "",
      "target_esphome_version": "",
      "failure_reason": ""
    },
    {
      "job_id": "9574228ac456",
      "configuration": "proxy_kitchen.yaml",
      "job_type": "upload",
      "status": "completed",
      "created_at": "2026-07-09T21:35:21.838622+00:00",
      "started_at": "2026-07-09T21:35:21.838727+00:00",
      "completed_at": "2026-07-09T21:35:38.153638+00:00",
      "exit_code": 0,
      "error": null,
      "port": "OTA",
      "flash_bootloader": false,
      "is_deferred_install": false,
      "new_name": "",
      "depends_on": "",
      "dependency_released": false,
      "progress": 100,
      "remote_peer": "",
      "remote_job_id": "",
      "remote_peer_label": "",
      "device_name": "",
      "device_friendly_name": "",
      "source": "local",
      "source_pin_sha256": "",
      "source_label": "",
      "source_esphome_version": "",
      "target_esphome_version": "",
      "failure_reason": ""
    },
    {
      "job_id": "b43ec984d562",
      "configuration": "proxy_sleep.yaml",
      "job_type": "compile",
      "status": "completed",
      "created_at": "2026-07-09T21:35:21.838098+00:00",
      "started_at": "2026-07-09T21:35:21.839315+00:00",
      "completed_at": "2026-07-09T21:37:35.517302+00:00",
      "exit_code": 0,
      "error": null,
      "port": "",
      "flash_bootloader": false,
      "is_deferred_install": false,
      "new_name": "",
      "depends_on": "",
      "dependency_released": false,
      "progress": null,
      "remote_peer": "",
      "remote_job_id": "",
      "remote_peer_label": "",
      "device_name": "",
      "device_friendly_name": "",
      "source": "local",
      "source_pin_sha256": "",
      "source_label": "",
      "source_esphome_version": "",
      "target_esphome_version": "",
      "failure_reason": ""
    },
    {
      "job_id": "ff4285e983cc",
      "configuration": "proxy_kitchen.yaml",
      "job_type": "compile",
      "status": "completed",
      "created_at": "2026-07-09T21:32:58.309991+00:00",
      "started_at": "2026-07-09T21:32:58.310196+00:00",
      "completed_at": "2026-07-09T21:35:21.835218+00:00",
      "exit_code": 0,
      "error": null,
      "port": "",
      "flash_bootloader": false,
      "is_deferred_install": false,
      "new_name": "",
      "depends_on": "",
      "dependency_released": false,
      "progress": null,
      "remote_peer": "",
      "remote_job_id": "",
      "remote_peer_label": "",
      "device_name": "",
      "device_friendly_name": "",
      "source": "local",
      "source_pin_sha256": "",
      "source_label": "",
      "source_esphome_version": "",
      "target_esphome_version": "",
      "failure_reason": ""
    },
    {
      "job_id": "117811ba2afe",
      "configuration": "m5stack-atom-echo-54cbf0.yaml",
      "job_type": "upload",
      "status": "cancelled",
      "created_at": "2026-06-22T12:04:20.669285+00:00",
      "started_at": null,
      "completed_at": "2026-06-22T12:04:24.258986+00:00",
      "exit_code": null,
      "error": "prerequisite job did not complete successfully",
      "port": "OTA",
      "flash_bootloader": false,
      "is_deferred_install": false,
      "new_name": "",
      "depends_on": "e426d9f69400",
      "dependency_released": false,
      "progress": null,
      "remote_peer": "",
      "remote_job_id": "",
      "remote_peer_label": "",
      "device_name": "",
      "device_friendly_name": "",
      "source": "local",
      "source_pin_sha256": "",
      "source_label": "",
      "source_esphome_version": "",
      "target_esphome_version": "",
      "failure_reason": ""
    },
    {
      "job_id": "e426d9f69400",
      "configuration": "m5stack-atom-echo-54cbf0.yaml",
      "job_type": "compile",
      "status": "cancelled",
      "created_at": "2026-06-22T12:04:20.669260+00:00",
      "started_at": "2026-06-22T12:04:20.669749+00:00",
      "completed_at": "2026-06-22T12:04:24.258927+00:00",
      "exit_code": -15,
      "error": null,
      "port": "",
      "flash_bootloader": false,
      "is_deferred_install": false,
      "new_name": "",
      "depends_on": "",
      "dependency_released": false,
      "progress": null,
      "remote_peer": "",
      "remote_job_id": "",
      "remote_peer_label": "",
      "device_name": "",
      "device_friendly_name": "",
      "source": "local",
      "source_pin_sha256": "",
      "source_label": "",
      "source_esphome_version": "",
      "target_esphome_version": "",
      "failure_reason": ""
    },
    {
      "job_id": "34e7620350ba",
      "configuration": "s3box_main.yaml",
      "job_type": "clean",
      "status": "completed",
      "created_at": "2026-06-26T12:06:56.052382+00:00",
      "started_at": "2026-06-26T12:06:56.085692+00:00",
      "completed_at": "2026-06-26T12:06:56.873431+00:00",
      "exit_code": 0,
      "error": null,
      "port": "",
      "flash_bootloader": false,
      "is_deferred_install": false,
      "new_name": "",
      "depends_on": "",
      "dependency_released": false,
      "progress": null,
      "remote_peer": "",
      "remote_job_id": "",
      "remote_peer_label": "",
      "device_name": "",
      "device_friendly_name": "",
      "source": "local",
      "source_pin_sha256": "",
      "source_label": "",
      "source_esphome_version": "",
      "target_esphome_version": "",
      "failure_reason": ""
    }
  ],
  "s3box_main.yaml": {
    "mac_address": "74:4D:BD:2E:8B:78"
  }
}
