{
  "name": "2010s & 2020s Hits",
  "version": "1.3",
  "tags": [
    "pop",
    "charts",
    "2010s",
    "2020s"
  ],
  "language": "en",
  "author": "Beatify Community",
  "added_date": "2026-05-15",
  "description": "The big chart hits of the 2010s and 2020s — filling Beatify's decade gap between the 2000s playlist and today. Sourced from the German Hitster song pool (#892).",
  "songs": [
    {
      "artist": "Dermot Kennedy",
      "title": "Power Over Me",
      "year": 2019,
      "isrc": "USUG11802208",
      "uri": "spotify:track:3CNLrZJST54nE4PUkS83Sl",
      "uri_apple_music": "applemusic://track/1518633270",
      "uri_apple_music_by_region": {
        "us": "applemusic://track/1518633270",
        "de": "applemusic://track/1518633270",
        "gb": "applemusic://track/1518633270",
        "fr": "applemusic://track/1518633270",
        "es": "applemusic://track/1518633270",
        "nl": "applemusic://track/1518633270",
        "it": "applemusic://track/1518633270"
      },
      "uri_youtube_music": "https://music.youtube.com/watch?v=mZxGIfDWzr4",
      "uri_tidal": null,
      "uri_deezer": "deezer://track/610861462",
      "fun_fact": "A chart hit by Dermot Kennedy (2019).",
      "fun_fact_de": "Ein Chart-Hit von Dermot Kennedy (2019).",
      "fun_fact_es": "Un éxito de Dermot Kennedy (2019).",
      "fun_fact_fr": "Un tube de Dermot Kennedy (2019).",
      "fun_fact_nl": "Een chart-hit van Dermot Kennedy (2019)."
    },
    {
      "artist": "Galantis",
      "title": "No Money",
      "year": 2016,
      "isrc": "USAT21600941",
      "uri": "spotify:track:0gb1J5UrTpzaU1s3nupgCd",
      "uri_apple_music": "applemusic://track/1843374417",
      "uri_apple_music_by_region": {
        "us": "applemusic://track/1843374417",
        "de": "applemusic://track/1843374417",
        "gb": "applemusic://track/1843374417",
        "fr": "applemusic://track/1843374417",
        "es": "applemusic://track/1843374417",
        "nl": "applemusic://track/1843374417",
        "it": "applemusic://track/1843374417"
      },
      "uri_youtube_music": "https://music.youtube.com/watch?v=LsCHjlYw2oM",
      "uri_tidal": null,
      "uri_deezer": "deezer://track/121107876",
      "fun_fact": "A chart hit by Galantis (2016).",
      "fun_fact_de": "Ein Chart-Hit von Galantis (2016).",
      "fun_fact_es": "Un éxito de Galantis (2016).",
      "fun_fact_fr": "Un tube de Galantis (2016).",
      "fun_fact_nl": "Een chart-hit van Galantis (2016)."
    },
    {
      "artist": "BTS",
      "title": "Dynamite",
      "year": 2020,
      "isrc": "QM7282022872",
      "uri": "spotify:track:4saklk6nie3yiGePpBwUoc",
      "uri_apple_music": "applemusic://track/1627575419",
      "uri_apple_music_by_region": {
        "us": "applemusic://track/1627575419",
        "de": "applemusic://track/1627575419",
        "gb": "applemusic://track/1627575419",
        "fr": "applemusic://track/1627575419",
        "es": "applemusic://track/1627575419",
        "nl": "applemusic://track/1627575419",
        "it": "applemusic://track/1627575419"
      },
      "uri_youtube_music": "https://music.youtube.com/watch?v=HaEYUJ2aRHs",
      "uri_tidal": null,
      "uri_deezer": "deezer://track/1564465082",
      "fun_fact": "A chart hit by BTS (2020).",
      "fun_fact_de": "Ein Chart-Hit von BTS (2020).",
      "fun_fact_es": "Un éxito de BTS (2020).",
      "fun_fact_fr": "Un tube de BTS (2020).",
      "fun_fact_nl": "Een chart-hit van BTS (2020)."
    },
    {
      "artist": "Jawsh 685",
      "title": "Savage Love (Laxed - Siren Beat)",
      "year": 2020,
      "isrc": "USSM12003798",
      "uri": "spotify:track:1xQ6trAsedVPCdbtDAmk0c",
      "uri_apple_music": "applemusic://track/1517696110",
      "uri_apple_music_by_region": {
        "us": "applemusic://track/1517696110",
        "de": "applemusic://track/1517696110",
        "gb": "applemusic://track/1517696110",
        "fr": "applemusic://track/1517696110",
        "es": "applemusic://track/1517696110",
        "nl": "applemusic://track/1517696110",
        "it": "applemusic://track/1517696110"
      },
      "uri_youtube_music": "https://music.youtube.com/watch?v=zfvfxA166eQ",
      "uri_tidal": null,
      "uri_deezer": "deezer://track/986939372",
      "alt_artists": [
        "Jason Derulo"
      ],
      "fun_fact": "A chart hit by Jawsh 685 (2020).",
      "fun_fact_de": "Ein Chart-Hit von Jawsh 685 (2020).",
      "fun_fact_es": "Un éxito de Jawsh 685 (2020).",
      "fun_fact_fr": "Un tube de Jawsh 685 (2020).",
      "fun_fact_nl": "Een chart-hit van Jawsh 685 (2020)."
    },
    {
      "artist": "Sia",
      "title": "Santa's Coming for Us",
      "year": 2017,
      "isrc": "USAT21704210",
      "uri": "spotify:track:3AlpkljBS1AU7HFVPms8K6",
      "uri_apple_music": "applemusic://track/1730454802",
      "uri_apple_music_by_region": {
        "us": "applemusic://track/1730454802",
        "de": "applemusic://track/1730454802",
        "gb": "applemusic://track/1730454802",
        "fr": "applemusic://track/1730454802",
        "es": "applemusic://track/1730454802",
        "nl": "applemusic://track/1730454802",
        "it": "applemusic://track/1730454802"
      },
      "uri_youtube_music": "https://music.youtube.com/watch?v=l8JSq9BJwM8",
      "uri_tidal": null,
      "uri_deezer": "deezer://track/576178912",
      "fun_fact": "A chart hit by Sia (2017).",
      "fun_fact_de": "Ein Chart-Hit von Sia (2017).",
      "fun_fact_es": "Un éxito de Sia (2017).",
      "fun_fact_fr": "Un tube de Sia (2017).",
      "fun_fact_nl": "Een chart-hit van Sia (2017)."
    },
    {
      "artist": "Jess Glynne",
      "title": "Hold My Hand",
      "year": 2015,
      "isrc": "GBAHS1500049",
      "uri": "spotify:track:1i1rNVtxbE7rdFfpHuNq2j",
      "uri_apple_music": "applemusic://track/1824437915",
      "uri_apple_music_by_region": {
        "us": "applemusic://track/1824437915",
        "de": "applemusic://track/1824437915",
        "gb": "applemusic://track/1824437915",
        "fr": "applemusic://track/1824437915",
        "es": "applemusic://track/1824437915",
        "nl": "applemusic://track/1824437915",
        "it": "applemusic://track/1824437915"
      },
      "uri_youtube_music": "https://music.youtube.com/watch?v=QD3CQlFGTRU",
      "uri_tidal": null,
      "uri_deezer": "deezer://track/95973024",
      "fun_fact": "A chart hit by Jess Glynne (2015).",
      "fun_fact_de": "Ein Chart-Hit von Jess Glynne (2015).",
      "fun_fact_es": "Un éxito de Jess Glynne (2015).",
      "fun_fact_fr": "Un tube de Jess Glynne (2015).",
      "fun_fact_nl": "Een chart-hit van Jess Glynne (2015)."
    },
    {
      "artist": "Daddy Yankee",
      "title": "Con Calma",
      "year": 2019,
      "isrc": "US2BU1900125",
      "uri": "spotify:track:5w9c2J52mkdntKOmRLeM2m",
      "uri_apple_music": "applemusic://track/1817038660",
      "uri_apple_music_by_region": {
        "us": "applemusic://track/1817038660",
        "de": "applemusic://track/1817038660",
        "gb": "applemusic://track/1817038660",
        "fr": "applemusic://track/1817038660",
        "es": "applemusic://track/1817038660",
        "nl": "applemusic://track/1817038660",
        "it": "applemusic://track/1817038660"
      },
      "uri_youtube_music": "https://music.youtube.com/watch?v=GQwj_FRntp8",
      "uri_tidal": null,
      "uri_deezer": "deezer://track/619949882",
      "alt_artists": [
        "Snow"
      ],
      "fun_fact": "A chart hit by Daddy Yankee (2019).",
      "fun_fact_de": "Ein Chart-Hit von Daddy Yankee (2019).",
      "fun_fact_es": "Un éxito de Daddy Yankee (2019).",
      "fun_fact_fr": "Un tube de Daddy Yankee (2019).",
      "fun_fact_nl": "Een chart-hit van Daddy Yankee (2019)."
    },
    {
      "artist": "Yolanda Be Cool",
      "title": "We No Speak Americano",
      "year": 2010,
      "isrc": "AUXN21740665",
      "uri": "spotify:track:0CJ1quCQhVX9Ax2jYwwovA",
      "uri_apple_music": "applemusic://track/1360104027",
      "uri_apple_music_by_region": {
        "us": "applemusic://track/1360104027",
        "de": "applemusic://track/1360104027",
        "gb": "applemusic://track/1360104027",
        "fr": "applemusic://track/1360104027",
        "es": "applemusic://track/1360104027",
        "nl": "applemusic://track/1360104027",
        "it": "applemusic://track/1360104027"
      },
      "uri_youtube_music": "https://music.youtube.com/watch?v=lygg5Ju0nNU",
      "uri_tidal": null,
      "uri_deezer": "deezer://track/474915622",
      "alt_artists": [
        "DCup"
      ],
      "fun_fact": "A chart hit by Yolanda Be Cool (2010).",
      "fun_fact_de": "Ein Chart-Hit von Yolanda Be Cool (2010).",
      "fun_fact_es": "Un éxito de Yolanda Be Cool (2010).",
      "fun_fact_fr": "Un tube de Yolanda Be Cool (2010).",
      "fun_fact_nl": "Een chart-hit van Yolanda Be Cool (2010)."
    },
    {
      "artist": "Becky G",
      "title": "Arranca (feat. Omega)",
      "year": 2023,
      "isrc": "USRC12300209",
      "uri": "spotify:track:6IdcyYfBz9LG3SWIKVyNgh",
      "uri_apple_music": "applemusic://track/1674907698",
      "uri_apple_music_by_region": {
        "us": "applemusic://track/1674907698",
        "de": "applemusic://track/1674907698",
        "gb": "applemusic://track/1674907698",
        "fr": "applemusic://track/1674907698",
        "es": "applemusic://track/1674907698",
        "nl": "applemusic://track/1757602735",
        "it": "applemusic://track/1674907698"
      },
      "uri_youtube_music": "https://music.youtube.com/watch?v=dv8V-w-Pu1A",
      "uri_tidal": null,
      "uri_deezer": "deezer://track/2170492547",
      "alt_artists": [
        "Omega"
      ],
      "fun_fact": "A chart hit by Becky G (2023).",
      "fun_fact_de": "Ein Chart-Hit von Becky G (2023).",
      "fun_fact_es": "Un éxito de Becky G (2023).",
      "fun_fact_fr": "Un tube de Becky G (2023).",
      "fun_fact_nl": "Een chart-hit van Becky G (2023)."
    },
    {
      "artist": "Nina Chuba",
      "title": "Wildberry Lillet",
      "year": 2022,
      "isrc": "DEE862201008",
      "uri": "spotify:track:6yeZM8gyykjaf8w0GqRfK4",
      "uri_apple_music": "applemusic://track/1643531791",
      "uri_apple_music_by_region": {
        "us": "applemusic://track/1643531791",
        "de": "applemusic://track/1643531791",
        "gb": "applemusic://track/1643531791",
        "fr": "applemusic://track/1643531791",
        "es": "applemusic://track/1643531791",
        "nl": "applemusic://track/1643531791",
        "it": "applemusic://track/1643531791"
      },
      "uri_youtube_music": "https://music.youtube.com/watch?v=Ag4EXrgDPzc",
      "uri_tidal": null,
      "uri_deezer": "deezer://track/1841649517",
      "fun_fact": "A chart hit by Nina Chuba (2022).",
      "fun_fact_de": "Ein Chart-Hit von Nina Chuba (2022).",
      "fun_fact_es": "Un éxito de Nina Chuba (2022).",
      "fun_fact_fr": "Un tube de Nina Chuba (2022).",
      "fun_fact_nl": "Een chart-hit van Nina Chuba (2022)."
    },
    {
      "artist": "DJ Snake",
      "title": "Let Me Love You",
      "year": 2016,
      "isrc": "QMZSY1600015",
      "uri": "spotify:track:0lYBSQXN6rCTvUZvg9S0lU",
      "uri_apple_music": "applemusic://track/1566250669",
      "uri_apple_music_by_region": {
        "us": "applemusic://track/1566250669",
        "de": "applemusic://track/1566250669",
        "gb": "applemusic://track/1566250669",
        "fr": "applemusic://track/1566250669",
        "es": "applemusic://track/1566250669",
        "nl": "applemusic://track/1566250669",
        "it": "applemusic://track/1566250669"
      },
      "uri_youtube_music": "https://music.youtube.com/watch?v=rJ0D1GbDq1Q",
      "uri_tidal": null,
      "uri_deezer": "deezer://track/129632340",
      "alt_artists": [
        "Justin Bieber"
      ],
      "fun_fact": "A chart hit by DJ Snake (2016).",
      "fun_fact_de": "Ein Chart-Hit von DJ Snake (2016).",
      "fun_fact_es": "Un éxito de DJ Snake (2016).",
      "fun_fact_fr": "Un tube de DJ Snake (2016).",
      "fun_fact_nl": "Een chart-hit van DJ Snake (2016)."
    },
    {
      "artist": "Dua Lipa",
      "title": "New Rules",
      "year": 2018,
      "isrc": "DEUM71601962",
      "uri": "spotify:track:2ekn2ttSfGqwhhate0LSR0",
      "uri_apple_music": "applemusic://track/1435139360",
      "uri_apple_music_by_region": {
        "us": null,
        "de": "applemusic://track/1435139360",
        "gb": null,
        "fr": null,
        "es": null,
        "nl": null,
        "it": null
      },
      "uri_youtube_music": "https://music.youtube.com/watch?v=XmxL8IaC0MQ",
      "uri_tidal": null,
      "uri_deezer": "deezer://track/568119562",
      "fun_fact": "A chart hit by Dua Lipa (2018).",
      "fun_fact_de": "Ein Chart-Hit von Dua Lipa (2018).",
      "fun_fact_es": "Un éxito de Dua Lipa (2018).",
      "fun_fact_fr": "Un tube de Dua Lipa (2018).",
      "fun_fact_nl": "Een chart-hit van Dua Lipa (2018)."
    },
    {
      "artist": "Armin van Buuren",
      "title": "Sunny Days",
      "year": 2017,
      "isrc": "NLF711705042",
      "uri": "spotify:track:6RrUUleT9JI0KQHZYBdJMB",
      "uri_apple_music": "applemusic://track/1270202119",
      "uri_apple_music_by_region": {
        "us": "applemusic://track/1270202119",
        "de": "applemusic://track/1270202119",
        "gb": "applemusic://track/1478926055",
        "fr": "applemusic://track/1270202119",
        "es": "applemusic://track/1478926055",
        "nl": "applemusic://track/1843185367",
        "it": "applemusic://track/1478926055"
      },
      "uri_youtube_music": "https://music.youtube.com/watch?v=v3rLqmxCyFg",
      "uri_tidal": null,
      "uri_deezer": "deezer://track/371903741",
      "alt_artists": [
        "Josh Cumbee"
      ],
      "fun_fact": "A chart hit by Armin van Buuren (2017).",
      "fun_fact_de": "Ein Chart-Hit von Armin van Buuren (2017).",
      "fun_fact_es": "Un éxito de Armin van Buuren (2017).",
      "fun_fact_fr": "Un tube de Armin van Buuren (2017).",
      "fun_fact_nl": "Een chart-hit van Armin van Buuren (2017)."
    },
    {
      "artist": "Imagine Dragons",
      "title": "On Top Of The World",
      "year": 2013,
      "isrc": "USUM71201073",
      "uri": "spotify:track:6KuHjfXHkfnIjdmcIvt9r0",
      "uri_apple_music": "applemusic://track/1440873406",
      "uri_apple_music_by_region": {
        "us": "applemusic://track/1440873406",
        "de": "applemusic://track/1714510316",
        "gb": "applemusic://track/1714510316",
        "fr": "applemusic://track/1714510316",
        "es": "applemusic://track/1714510316",
        "nl": "applemusic://track/1714510316",
        "it": "applemusic://track/1714510316"
      },
      "uri_youtube_music": "https://music.youtube.com/watch?v=dj86haGuI8w",
      "uri_tidal": null,
      "uri_deezer": "deezer://track/63510362",
      "fun_fact": "A chart hit by Imagine Dragons (2013).",
      "fun_fact_de": "Ein Chart-Hit von Imagine Dragons (2013).",
      "fun_fact_es": "Un éxito de Imagine Dragons (2013).",
      "fun_fact_fr": "Un tube de Imagine Dragons (2013).",
      "fun_fact_nl": "Een chart-hit van Imagine Dragons (2013)."
    },
    {
      "artist": "Owl City",
      "title": "Good Time",
      "year": 2012,
      "isrc": "USUM71206288",
      "uri": "spotify:track:1kPpge9JDLpcj15qgrPbYX",
      "uri_apple_music": "applemusic://track/1551388182",
      "uri_apple_music_by_region": {
        "us": "applemusic://track/1551388182",
        "de": "applemusic://track/1551388182",
        "gb": "applemusic://track/1551388182",
        "fr": "applemusic://track/1551388182",
        "es": "applemusic://track/1551388182",
        "nl": "applemusic://track/1551388182",
        "it": "applemusic://track/1551388182"
      },
      "uri_youtube_music": "https://music.youtube.com/watch?v=zGipbUYrUCQ",
      "uri_tidal": null,
      "uri_deezer": "deezer://track/53825251",
      "alt_artists": [
        "Carly Rae Jepsen"
      ],
      "fun_fact": "A chart hit by Owl City (2012).",
      "fun_fact_de": "Ein Chart-Hit von Owl City (2012).",
      "fun_fact_es": "Un éxito de Owl City (2012).",
      "fun_fact_fr": "Un tube de Owl City (2012).",
      "fun_fact_nl": "Een chart-hit van Owl City (2012)."
    },
    {
      "artist": "Rudimental",
      "title": "Waiting All Night (feat. Ella Eyre)",
      "year": 2013,
      "isrc": "GBAHS1200493",
      "uri": "spotify:track:6yraFyhgbavO2amB2lhpfi",
      "uri_apple_music": "applemusic://track/1835099678",
      "uri_apple_music_by_region": {
        "us": "applemusic://track/1835099678",
        "de": "applemusic://track/1835099678",
        "gb": "applemusic://track/1835099678",
        "fr": "applemusic://track/1835099678",
        "es": "applemusic://track/1835099678",
        "nl": "applemusic://track/1835099678",
        "it": "applemusic://track/1835099678"
      },
      "uri_youtube_music": "https://music.youtube.com/watch?v=N5KEtQlWzEg",
      "uri_tidal": null,
      "uri_deezer": "deezer://track/65735114",
      "alt_artists": [
        "Ella Eyre"
      ],
      "fun_fact": "A chart hit by Rudimental (2013).",
      "fun_fact_de": "Ein Chart-Hit von Rudimental (2013).",
      "fun_fact_es": "Un éxito de Rudimental (2013).",
      "fun_fact_fr": "Un tube de Rudimental (2013).",
      "fun_fact_nl": "Een chart-hit van Rudimental (2013)."
    },
    {
      "artist": "Calvin Harris",
      "title": "By Your Side (feat. Tom Grennan)",
      "year": 2021,
      "isrc": "GBARL2100439",
      "uri": "spotify:track:0vR2rIVORmgeKiGIgNT0fV",
      "uri_apple_music": "applemusic://track/1761397067",
      "uri_apple_music_by_region": {
        "us": "applemusic://track/1761397067",
        "de": "applemusic://track/1761397067",
        "gb": "applemusic://track/1761397067",
        "fr": "applemusic://track/1761397067",
        "es": "applemusic://track/1761397067",
        "nl": "applemusic://track/1761397067",
        "it": "applemusic://track/1761397067"
      },
      "uri_youtube_music": "https://music.youtube.com/watch?v=NLyKhp-4Y-0",
      "uri_tidal": null,
      "uri_deezer": "deezer://track/1371887182",
      "alt_artists": [
        "Tom Grennan"
      ],
      "fun_fact": "A chart hit by Calvin Harris (2021).",
      "fun_fact_de": "Ein Chart-Hit von Calvin Harris (2021).",
      "fun_fact_es": "Un éxito de Calvin Harris (2021).",
      "fun_fact_fr": "Un tube de Calvin Harris (2021).",
      "fun_fact_nl": "Een chart-hit van Calvin Harris (2021)."
    },
    {
      "artist": "Tones And I",
      "title": "Dance Monkey",
      "year": 2019,
      "isrc": "QZES71982312",
      "uri": "spotify:track:5ZULALImTm80tzUbYQYM9d",
      "uri_apple_music": "applemusic://track/1807709656",
      "uri_apple_music_by_region": {
        "us": "applemusic://track/1807709656",
        "de": "applemusic://track/1857702817",
        "gb": "applemusic://track/1807709656",
        "fr": "applemusic://track/1857702817",
        "es": "applemusic://track/1807709656",
        "nl": "applemusic://track/1807709656",
        "it": "applemusic://track/1807709656"
      },
      "uri_youtube_music": "https://music.youtube.com/watch?v=Hx4nWW9z0ig",
      "uri_tidal": null,
      "uri_deezer": "deezer://track/739870792",
      "fun_fact": "A chart hit by Tones And I (2019).",
      "fun_fact_de": "Ein Chart-Hit von Tones And I (2019).",
      "fun_fact_es": "Un éxito de Tones And I (2019).",
      "fun_fact_fr": "Un tube de Tones And I (2019).",
      "fun_fact_nl": "Een chart-hit van Tones And I (2019)."
    },
    {
      "artist": "Martin Garrix",
      "title": "High On Life (feat. Bonn)",
      "year": 2018,
      "isrc": "NLM5S1800265",
      "uri": "spotify:track:4ut5G4rgB1ClpMTMfjoIuy",
      "uri_apple_music": "applemusic://track/1416740913",
      "uri_apple_music_by_region": {
        "us": "applemusic://track/1416740913",
        "de": "applemusic://track/1416740913",
        "gb": "applemusic://track/1416740913",
        "fr": "applemusic://track/1416740913",
        "es": "applemusic://track/1416740913",
        "nl": "applemusic://track/1790923388",
        "it": "applemusic://track/1416740913"
      },
      "uri_youtube_music": "https://music.youtube.com/watch?v=K2UAIvQ_lNY",
      "uri_tidal": null,
      "uri_deezer": "deezer://track/532182272",
      "alt_artists": [
        "Bonn"
      ],
      "fun_fact": "A chart hit by Martin Garrix (2018).",
      "fun_fact_de": "Ein Chart-Hit von Martin Garrix (2018).",
      "fun_fact_es": "Un éxito de Martin Garrix (2018).",
      "fun_fact_fr": "Un tube de Martin Garrix (2018).",
      "fun_fact_nl": "Een chart-hit van Martin Garrix (2018)."
    },
    {
      "artist": "Andreas Gabalier",
      "title": "Hallihallo",
      "year": 2018,
      "isrc": "DEUM71801228",
      "uri": "spotify:track:0OPQRCqdgAfgghajirG91o",
      "uri_apple_music": "applemusic://track/6767693237",
      "uri_apple_music_by_region": {
        "us": "applemusic://track/6767693237",
        "de": "applemusic://track/6767693237",
        "gb": "applemusic://track/6767693237",
        "fr": "applemusic://track/6767693237",
        "es": "applemusic://track/6767693237",
        "nl": "applemusic://track/6767693237",
        "it": "applemusic://track/6767693237"
      },
      "uri_youtube_music": "https://music.youtube.com/watch?v=SZx4KF6CQFU",
      "uri_tidal": null,
      "uri_deezer": "deezer://track/552345022",
      "fun_fact": "A chart hit by Andreas Gabalier (2018).",
      "fun_fact_de": "Ein Chart-Hit von Andreas Gabalier (2018).",
      "fun_fact_es": "Un éxito de Andreas Gabalier (2018).",
      "fun_fact_fr": "Un tube de Andreas Gabalier (2018).",
      "fun_fact_nl": "Een chart-hit van Andreas Gabalier (2018)."
    },
    {
      "artist": "INNA",
      "title": "Sun Is Up",
      "year": 2011,
      "isrc": "ROROT1007301",
      "uri": "spotify:track:6V2qGKZWIR7xsbhFtUQdsn",
      "uri_apple_music": "applemusic://track/1834746991",
      "uri_apple_music_by_region": {
        "us": "applemusic://track/1834746991",
        "de": "applemusic://track/1834746991",
        "gb": "applemusic://track/1834746991",
        "fr": "applemusic://track/1834746991",
        "es": "applemusic://track/1834746991",
        "nl": "applemusic://track/1834746991",
        "it": "applemusic://track/1834746991"
      },
      "uri_youtube_music": "https://music.youtube.com/watch?v=U4CPl7mpxFw",
      "uri_tidal": null,
      "uri_deezer": "deezer://track/68985416",
      "fun_fact": "A chart hit by INNA (2011).",
      "fun_fact_de": "Ein Chart-Hit von INNA (2011).",
      "fun_fact_es": "Un éxito de INNA (2011).",
      "fun_fact_fr": "Un tube de INNA (2011).",
      "fun_fact_nl": "Een chart-hit van INNA (2011)."
    },
    {
      "artist": "Artemas",
      "title": "i like the way you kiss me",
      "year": 2024,
      "isrc": "QZJ842400387",
      "uri": "spotify:track:2GxrNKugF82CnoRFbQfzPf",
      "uri_apple_music": "applemusic://track/1756057163",
      "uri_apple_music_by_region": {
        "us": "applemusic://track/1756057163",
        "de": "applemusic://track/1756057163",
        "gb": "applemusic://track/1756057163",
        "fr": "applemusic://track/1756057163",
        "es": "applemusic://track/1781271810",
        "nl": "applemusic://track/1756057163",
        "it": "applemusic://track/1756057163"
      },
      "uri_youtube_music": "https://music.youtube.com/watch?v=jVBsM8CM0AE",
      "uri_tidal": null,
      "uri_deezer": "deezer://track/2706736172",
      "fun_fact": "A chart hit by Artemas (2024).",
      "fun_fact_de": "Ein Chart-Hit von Artemas (2024).",
      "fun_fact_es": "Un éxito de Artemas (2024).",
      "fun_fact_fr": "Un tube de Artemas (2024).",
      "fun_fact_nl": "Een chart-hit van Artemas (2024)."
    },
    {
      "artist": "Calvin Harris",
      "title": "One Kiss (with Dua Lipa)",
      "year": 2018,
      "isrc": null,
      "uri": "spotify:track:7ef4DlsgrMEH11cDZd32M6",
      "uri_apple_music": null,
      "uri_apple_music_by_region": {},
      "uri_youtube_music": "https://music.youtube.com/watch?v=XWCPbRsMb0Q",
      "uri_tidal": null,
      "uri_deezer": null,
      "alt_artists": [
        "Dua Lipa"
      ],
      "fun_fact": "A chart hit by Calvin Harris (2018).",
      "fun_fact_de": "Ein Chart-Hit von Calvin Harris (2018).",
      "fun_fact_es": "Un éxito de Calvin Harris (2018).",
      "fun_fact_fr": "Un tube de Calvin Harris (2018).",
      "fun_fact_nl": "Een chart-hit van Calvin Harris (2018)."
    },
    {
      "artist": "Jennifer Lopez",
      "title": "On The Floor",
      "year": 2011,
      "isrc": "USUM71100721",
      "uri": "spotify:track:3C0nOe05EIt1390bVABLyN",
      "uri_apple_music": "applemusic://track/1699868137",
      "uri_apple_music_by_region": {
        "us": "applemusic://track/1699868137",
        "de": "applemusic://track/1699868137",
        "gb": "applemusic://track/1699868137",
        "fr": "applemusic://track/1699868137",
        "es": "applemusic://track/1699868137",
        "nl": "applemusic://track/1699868137",
        "it": "applemusic://track/1699868137"
      },
      "uri_youtube_music": "https://music.youtube.com/watch?v=gDRL47NzG5o",
      "uri_tidal": null,
      "uri_deezer": "deezer://track/8930372",
      "alt_artists": [
        "Pitbull"
      ],
      "fun_fact": "A chart hit by Jennifer Lopez (2011).",
      "fun_fact_de": "Ein Chart-Hit von Jennifer Lopez (2011).",
      "fun_fact_es": "Un éxito de Jennifer Lopez (2011).",
      "fun_fact_fr": "Un tube de Jennifer Lopez (2011).",
      "fun_fact_nl": "Een chart-hit van Jennifer Lopez (2011)."
    },
    {
      "artist": "J Balvin",
      "title": "Mi Gente - Original Mix",
      "year": 2017,
      "isrc": "FR22F1701790",
      "uri": "spotify:track:7lHZVqUWCH19fUw0ZI2euy",
      "uri_apple_music": "applemusic://track/1598666433",
      "uri_apple_music_by_region": {
        "us": "applemusic://track/1598666433",
        "de": "applemusic://track/1460254778",
        "gb": "applemusic://track/1598666433",
        "fr": "applemusic://track/1248364550",
        "es": "applemusic://track/1598666433",
        "nl": "applemusic://track/1695722872",
        "it": "applemusic://track/1598666433"
      },
      "uri_youtube_music": "https://music.youtube.com/watch?v=_Za1vy3yDUc",
      "uri_tidal": null,
      "uri_deezer": "deezer://track/377718131",
      "alt_artists": [
        "Willy William"
      ],
      "fun_fact": "A chart hit by J Balvin (2017).",
      "fun_fact_de": "Ein Chart-Hit von J Balvin (2017).",
      "fun_fact_es": "Un éxito de J Balvin (2017).",
      "fun_fact_fr": "Un tube de J Balvin (2017).",
      "fun_fact_nl": "Een chart-hit van J Balvin (2017)."
    },
    {
      "artist": "Avicii",
      "title": "Levels - Radio Edit",
      "year": 2011,
      "isrc": "SEUM71100962",
      "uri": "spotify:track:5UqCQaDshqbIk3pkhy4Pjg",
      "uri_apple_music": "applemusic://track/1888263656",
      "uri_apple_music_by_region": {
        "us": "applemusic://track/1888263656",
        "de": "applemusic://track/1888263656",
        "gb": "applemusic://track/1888263656",
        "fr": "applemusic://track/1888263656",
        "es": "applemusic://track/1888263656",
        "nl": "applemusic://track/1888263656",
        "it": "applemusic://track/1888263656"
      },
      "uri_youtube_music": "https://music.youtube.com/watch?v=xAgv1mAyxr8",
      "uri_tidal": null,
      "uri_deezer": "deezer://track/14383880",
      "fun_fact": "A chart hit by Avicii (2011).",
      "fun_fact_de": "Ein Chart-Hit von Avicii (2011).",
      "fun_fact_es": "Un éxito de Avicii (2011).",
      "fun_fact_fr": "Un tube de Avicii (2011).",
      "fun_fact_nl": "Een chart-hit van Avicii (2011)."
    },
    {
      "artist": "Jessie J",
      "title": "Bang Bang",
      "year": 2014,
      "isrc": "USUM71409737",
      "uri": "spotify:track:0puf9yIluy9W0vpMEUoAnN",
      "uri_apple_music": "applemusic://track/1444896442",
      "uri_apple_music_by_region": {
        "us": "applemusic://track/1444896442",
        "de": "applemusic://track/1444896442",
        "gb": "applemusic://track/1442953253",
        "fr": "applemusic://track/1444896442",
        "es": "applemusic://track/1442884168",
        "nl": "applemusic://track/1444896442",
        "it": "applemusic://track/1442401366"
      },
      "uri_youtube_music": "https://music.youtube.com/watch?v=b0U-NcIWz1M",
      "uri_tidal": null,
      "uri_deezer": "deezer://track/81609384",
      "alt_artists": [
        "Ariana Grande",
        "Nicki Minaj"
      ],
      "fun_fact": "A chart hit by Jessie J (2014).",
      "fun_fact_de": "Ein Chart-Hit von Jessie J (2014).",
      "fun_fact_es": "Un éxito de Jessie J (2014).",
      "fun_fact_fr": "Un tube de Jessie J (2014).",
      "fun_fact_nl": "Een chart-hit van Jessie J (2014)."
    },
    {
      "artist": "Linkin Park",
      "title": "The Emptiness Machine",
      "year": 2024,
      "isrc": "USWB12403464",
      "uri": "spotify:track:2PnlsTsOTLE5jnBnNe2K0A",
      "uri_apple_music": "applemusic://track/1790697544",
      "uri_apple_music_by_region": {
        "us": "applemusic://track/1790697544",
        "de": "applemusic://track/1790697544",
        "gb": "applemusic://track/1790697544",
        "fr": "applemusic://track/1790697544",
        "es": "applemusic://track/1790697544",
        "nl": "applemusic://track/1790697544",
        "it": "applemusic://track/1790697544"
      },
      "uri_youtube_music": "https://music.youtube.com/watch?v=KBV_zpMm_0Q",
      "uri_tidal": null,
      "uri_deezer": "deezer://track/3068802261",
      "fun_fact": "A chart hit by Linkin Park (2024).",
      "fun_fact_de": "Ein Chart-Hit von Linkin Park (2024).",
      "fun_fact_es": "Un éxito de Linkin Park (2024).",
      "fun_fact_fr": "Un tube de Linkin Park (2024).",
      "fun_fact_nl": "Een chart-hit van Linkin Park (2024)."
    },
    {
      "artist": "Peggy Gou",
      "title": "(It Goes Like) Nanana - Edit",
      "year": 2023,
      "isrc": "GBBKS2300080",
      "uri": "spotify:track:23RoR84KodL5HWvUTneQ1w",
      "uri_apple_music": null,
      "uri_apple_music_by_region": {
        "us": null,
        "de": null,
        "gb": null,
        "fr": null,
        "es": null,
        "nl": null,
        "it": null
      },
      "uri_youtube_music": "https://music.youtube.com/watch?v=XOsY3W3dlI0",
      "uri_tidal": null,
      "uri_deezer": "deezer://track/2297911845",
      "fun_fact": "A chart hit by Peggy Gou (2023).",
      "fun_fact_de": "Ein Chart-Hit von Peggy Gou (2023).",
      "fun_fact_es": "Un éxito de Peggy Gou (2023).",
      "fun_fact_fr": "Un tube de Peggy Gou (2023).",
      "fun_fact_nl": "Een chart-hit van Peggy Gou (2023)."
    },
    {
      "artist": "Beyoncé",
      "title": "TEXAS HOLD 'EM",
      "year": 2024,
      "isrc": "USSM12401302",
      "uri": "spotify:track:0Z7nGFVCLfixWctgePsRk9",
      "uri_apple_music": "applemusic://track/1738363782",
      "uri_apple_music_by_region": {
        "us": "applemusic://track/1738363782",
        "de": "applemusic://track/1738363782",
        "gb": "applemusic://track/1738363782",
        "fr": "applemusic://track/1738363782",
        "es": "applemusic://track/1738363782",
        "nl": "applemusic://track/1738363782",
        "it": "applemusic://track/1738363782"
      },
      "uri_youtube_music": "https://music.youtube.com/watch?v=jSG3uy97VNA",
      "uri_tidal": null,
      "uri_deezer": "deezer://track/2658723742",
      "fun_fact": "A chart hit by Beyoncé (2024).",
      "fun_fact_de": "Ein Chart-Hit von Beyoncé (2024).",
      "fun_fact_es": "Un éxito de Beyoncé (2024).",
      "fun_fact_fr": "Un tube de Beyoncé (2024).",
      "fun_fact_nl": "Een chart-hit van Beyoncé (2024)."
    },
    {
      "artist": "Alan Walker",
      "title": "Faded",
      "year": 2015,
      "isrc": "NOG841549010",
      "uri": "spotify:track:698ItKASDavgwZ3WjaWjtz",
      "uri_apple_music": "applemusic://track/1445141316",
      "uri_apple_music_by_region": {
        "us": "applemusic://track/1445141316",
        "de": "applemusic://track/1445141316",
        "gb": "applemusic://track/1445141316",
        "fr": "applemusic://track/1445141316",
        "es": "applemusic://track/1445141316",
        "nl": "applemusic://track/1445141316",
        "it": "applemusic://track/1445141316"
      },
      "uri_youtube_music": "https://music.youtube.com/watch?v=pIWaVJPl0-c",
      "uri_tidal": null,
      "uri_deezer": "deezer://track/140295501",
      "fun_fact": "A chart hit by Alan Walker (2015).",
      "fun_fact_de": "Ein Chart-Hit von Alan Walker (2015).",
      "fun_fact_es": "Un éxito de Alan Walker (2015).",
      "fun_fact_fr": "Un tube de Alan Walker (2015).",
      "fun_fact_nl": "Een chart-hit van Alan Walker (2015)."
    },
    {
      "artist": "Conkarah",
      "title": "Banana - feat. Shaggy",
      "year": 2020,
      "isrc": "QMRSZ2001248",
      "uri": "spotify:track:0GUhPeExe5pXiGcBk03WSm",
      "uri_apple_music": "applemusic://track/1613393848",
      "uri_apple_music_by_region": {
        "us": "applemusic://track/1613393848",
        "de": "applemusic://track/1613393848",
        "gb": "applemusic://track/1613393848",
        "fr": "applemusic://track/1613393848",
        "es": "applemusic://track/1613393848",
        "nl": "applemusic://track/1613393848",
        "it": "applemusic://track/1613393848"
      },
      "uri_youtube_music": "https://music.youtube.com/watch?v=wERbBIdcT4Y",
      "uri_tidal": null,
      "uri_deezer": "deezer://track/3782886122",
      "alt_artists": [
        "Shaggy"
      ],
      "fun_fact": "A chart hit by Conkarah (2020).",
      "fun_fact_de": "Ein Chart-Hit von Conkarah (2020).",
      "fun_fact_es": "Un éxito de Conkarah (2020).",
      "fun_fact_fr": "Un tube de Conkarah (2020).",
      "fun_fact_nl": "Een chart-hit van Conkarah (2020)."
    },
    {
      "artist": "Kygo",
      "title": "Dancing Feet (feat. DNCE)",
      "year": 2022,
      "isrc": "USRC12200139",
      "uri": "spotify:track:4RAR8g8fZNB106ezUurnE0",
      "uri_apple_music": "applemusic://track/1653449011",
      "uri_apple_music_by_region": {
        "us": "applemusic://track/1653449011",
        "de": "applemusic://track/1653449011",
        "gb": "applemusic://track/1653449011",
        "fr": "applemusic://track/1653449011",
        "es": "applemusic://track/1653449011",
        "nl": "applemusic://track/1653449011",
        "it": "applemusic://track/1653449011"
      },
      "uri_youtube_music": "https://music.youtube.com/watch?v=l0dwuaAF3VI",
      "uri_tidal": null,
      "uri_deezer": "deezer://track/1661208732",
      "alt_artists": [
        "DNCE"
      ],
      "fun_fact": "A chart hit by Kygo (2022).",
      "fun_fact_de": "Ein Chart-Hit von Kygo (2022).",
      "fun_fact_es": "Un éxito de Kygo (2022).",
      "fun_fact_fr": "Un tube de Kygo (2022).",
      "fun_fact_nl": "Een chart-hit van Kygo (2022)."
    },
    {
      "artist": "Alexandra Stan",
      "title": "Mr. Saxobeat - Radio Edit",
      "year": 2011,
      "isrc": "ROCRP1002864",
      "uri": "spotify:track:3LWDPEXEaLBRGNLbdcbwBR",
      "uri_apple_music": "applemusic://track/1531503560",
      "uri_apple_music_by_region": {
        "us": "applemusic://track/1531503560",
        "de": "applemusic://track/1531503560",
        "gb": "applemusic://track/1531503560",
        "fr": "applemusic://track/1531503560",
        "es": "applemusic://track/1531503560",
        "nl": "applemusic://track/1531503560",
        "it": "applemusic://track/1531503560"
      },
      "uri_youtube_music": "https://music.youtube.com/watch?v=uYN0VbbQTP8",
      "uri_tidal": null,
      "uri_deezer": "deezer://track/1077700822",
      "fun_fact": "A chart hit by Alexandra Stan (2011).",
      "fun_fact_de": "Ein Chart-Hit von Alexandra Stan (2011).",
      "fun_fact_es": "Un éxito de Alexandra Stan (2011).",
      "fun_fact_fr": "Un tube de Alexandra Stan (2011).",
      "fun_fact_nl": "Een chart-hit van Alexandra Stan (2011)."
    },
    {
      "artist": "Madcon",
      "title": "Don't Worry (with Ray Dalton) - Radio Edit",
      "year": 2015,
      "isrc": "NO5281501010",
      "uri": "spotify:track:63CSozvYUEudPp12679UVF",
      "uri_apple_music": "applemusic://track/1614290677",
      "uri_apple_music_by_region": {
        "us": "applemusic://track/1614290677",
        "de": "applemusic://track/1614290677",
        "gb": "applemusic://track/1614290677",
        "fr": "applemusic://track/1614290677",
        "es": "applemusic://track/1094155267",
        "nl": "applemusic://track/1614290677",
        "it": "applemusic://track/1614290677"
      },
      "uri_youtube_music": "https://music.youtube.com/watch?v=Iv_xiCxXxR0",
      "uri_tidal": null,
      "uri_deezer": "deezer://track/97094250",
      "alt_artists": [
        "Ray Dalton"
      ],
      "fun_fact": "A chart hit by Madcon (2015).",
      "fun_fact_de": "Ein Chart-Hit von Madcon (2015).",
      "fun_fact_es": "Un éxito de Madcon (2015).",
      "fun_fact_fr": "Un tube de Madcon (2015).",
      "fun_fact_nl": "Een chart-hit van Madcon (2015)."
    },
    {
      "artist": "LMFAO",
      "title": "Sexy And I Know It",
      "year": 2011,
      "isrc": "USUM71108090",
      "uri": "spotify:track:0KXcsCinixGmfcXjBqfEis",
      "uri_apple_music": "applemusic://track/1680227537",
      "uri_apple_music_by_region": {
        "us": "applemusic://track/1680227537",
        "de": "applemusic://track/1680227537",
        "gb": "applemusic://track/1680227537",
        "fr": "applemusic://track/1680227537",
        "es": "applemusic://track/1680227537",
        "nl": "applemusic://track/1680227537",
        "it": "applemusic://track/1680227537"
      },
      "uri_youtube_music": "https://music.youtube.com/watch?v=evHIaUZ0KtQ",
      "uri_tidal": null,
      "uri_deezer": "deezer://track/12565421",
      "fun_fact": "A chart hit by LMFAO (2011).",
      "fun_fact_de": "Ein Chart-Hit von LMFAO (2011).",
      "fun_fact_es": "Un éxito de LMFAO (2011).",
      "fun_fact_fr": "Un tube de LMFAO (2011).",
      "fun_fact_nl": "Een chart-hit van LMFAO (2011)."
    },
    {
      "artist": "Christian Steiffen",
      "title": "Ich fühl' mich Disco",
      "year": 2012,
      "isrc": "DEA621301036",
      "uri": "spotify:track:2zUKhXh78KzEnC7NzigNjn",
      "uri_apple_music": "applemusic://track/1697183130",
      "uri_apple_music_by_region": {
        "us": "applemusic://track/1697183130",
        "de": "applemusic://track/1704192399",
        "gb": "applemusic://track/1697183130",
        "fr": "applemusic://track/1697183130",
        "es": "applemusic://track/1697183130",
        "nl": "applemusic://track/1697183130",
        "it": "applemusic://track/1697183130"
      },
      "uri_youtube_music": "https://music.youtube.com/watch?v=FZfj5iPy5wU",
      "uri_tidal": null,
      "uri_deezer": "deezer://track/71444147",
      "fun_fact": "A chart hit by Christian Steiffen (2013).",
      "fun_fact_de": "Ein Chart-Hit von Christian Steiffen (2013).",
      "fun_fact_es": "Un éxito de Christian Steiffen (2013).",
      "fun_fact_fr": "Un tube de Christian Steiffen (2013).",
      "fun_fact_nl": "Een chart-hit van Christian Steiffen (2013)."
    },
    {
      "artist": "Leony",
      "title": "Holding On",
      "year": 2023,
      "isrc": "DEN062300006",
      "uri": "spotify:track:6YexWyp9s0V0w1uGhtITsd",
      "uri_apple_music": "applemusic://track/1669545757",
      "uri_apple_music_by_region": {
        "us": "applemusic://track/1669545757",
        "de": "applemusic://track/1669545757",
        "gb": "applemusic://track/1669545757",
        "fr": "applemusic://track/1677236606",
        "es": "applemusic://track/1669545757",
        "nl": "applemusic://track/1677396850",
        "it": "applemusic://track/1675511597"
      },
      "uri_youtube_music": "https://music.youtube.com/watch?v=p674YL6KmyI",
      "uri_tidal": null,
      "uri_deezer": "deezer://track/2171888827",
      "fun_fact": "A chart hit by Leony (2023).",
      "fun_fact_de": "Ein Chart-Hit von Leony (2023).",
      "fun_fact_es": "Un éxito de Leony (2023).",
      "fun_fact_fr": "Un tube de Leony (2023).",
      "fun_fact_nl": "Een chart-hit van Leony (2023)."
    },
    {
      "artist": "Alcazar",
      "title": "Crying At the Discoteque",
      "year": 2000,
      "isrc": "DEZ921200553",
      "uri": "spotify:track:5UcMexhqzhHXwGvYuA6kVj",
      "uri_apple_music": "applemusic://track/556437629",
      "uri_apple_music_by_region": {
        "us": "applemusic://track/556437629",
        "de": "applemusic://track/556437629",
        "gb": "applemusic://track/556437629",
        "fr": "applemusic://track/556437629",
        "es": "applemusic://track/556437629",
        "nl": "applemusic://track/556437629",
        "it": "applemusic://track/556437629"
      },
      "uri_youtube_music": "https://music.youtube.com/watch?v=a1fFwOXBxik",
      "uri_tidal": null,
      "uri_deezer": "deezer://track/57286181",
      "fun_fact": "A chart hit by Alcazar (2000).",
      "fun_fact_de": "Ein Chart-Hit von Alcazar (2000).",
      "fun_fact_es": "Un éxito de Alcazar (2000).",
      "fun_fact_fr": "Un tube de Alcazar (2000).",
      "fun_fact_nl": "Een chart-hit van Alcazar (2000)."
    },
    {
      "artist": "Imany",
      "title": "Don't Be So Shy - Filatov & Karas Remix",
      "year": 2017,
      "isrc": "FR9W11515482",
      "uri": "spotify:track:00vk0sEfb6mr2ehwSw0Uhn",
      "uri_apple_music": "applemusic://track/1711711223",
      "uri_youtube_music": "https://music.youtube.com/watch?v=b1_B-IKEufg",
      "uri_tidal": null,
      "uri_deezer": "deezer://track/444887352",
      "alt_artists": [
        "Filatov & Karas"
      ],
      "fun_fact": "A chart hit by Imany (2017).",
      "fun_fact_de": "Ein Chart-Hit von Imany (2017).",
      "fun_fact_es": "Un éxito de Imany (2017).",
      "fun_fact_fr": "Un tube de Imany (2017).",
      "fun_fact_nl": "Een chart-hit van Imany (2017)."
    },
    {
      "artist": "OMI",
      "title": "Cheerleader (Felix Jaehn Remix) - Radio Edit",
      "year": 2014,
      "isrc": "USUS11202574",
      "uri": "spotify:track:4fTHdMTq0Znl3djLI1Typn",
      "uri_apple_music": "applemusic://track/1712919358",
      "uri_apple_music_by_region": {
        "us": "applemusic://track/1712919358",
        "de": "applemusic://track/1001571198",
        "gb": "applemusic://track/1009324144",
        "fr": "applemusic://track/1008966385",
        "es": "applemusic://track/1003578321",
        "nl": "applemusic://track/1656111039",
        "it": "applemusic://track/1062031902"
      },
      "uri_youtube_music": "https://music.youtube.com/watch?v=VIUKdjDNbdE",
      "uri_tidal": null,
      "uri_deezer": "deezer://track/78098991",
      "alt_artists": [
        "Felix Jaehn"
      ],
      "fun_fact": "A chart hit by OMI (2014).",
      "fun_fact_de": "Ein Chart-Hit von OMI (2014).",
      "fun_fact_es": "Un éxito de OMI (2014).",
      "fun_fact_fr": "Un tube de OMI (2014).",
      "fun_fact_nl": "Een chart-hit van OMI (2014)."
    },
    {
      "artist": "Die Atzen",
      "title": "Disco Pogo",
      "year": 2010,
      "isrc": "DEN060901764",
      "uri": "spotify:track:1v5ux3K8vE1CWxDa0PVyGu",
      "uri_apple_music": "applemusic://track/1566573897",
      "uri_apple_music_by_region": {
        "us": "applemusic://track/1566573897",
        "de": "applemusic://track/1566573897",
        "gb": "applemusic://track/1566573897",
        "fr": "applemusic://track/1566573897",
        "es": "applemusic://track/1566573897",
        "nl": "applemusic://track/1842916717",
        "it": "applemusic://track/1566573897"
      },
      "uri_youtube_music": "https://music.youtube.com/watch?v=9u3FC1E6RMk",
      "uri_tidal": null,
      "uri_deezer": "deezer://track/1366251182",
      "fun_fact": "A chart hit by Die Atzen (2010).",
      "fun_fact_de": "Ein Chart-Hit von Die Atzen (2010).",
      "fun_fact_es": "Un éxito de Die Atzen (2010).",
      "fun_fact_fr": "Un tube de Die Atzen (2010).",
      "fun_fact_nl": "Een chart-hit van Die Atzen (2010)."
    },
    {
      "artist": "Twenty One Pilots",
      "title": "Stressed Out",
      "year": 2015,
      "isrc": "USAT21500597",
      "uri": "spotify:track:3CRDbSIZ4r5MsZ0YwxuEkn",
      "uri_apple_music": "applemusic://track/1633685561",
      "uri_apple_music_by_region": {
        "us": "applemusic://track/1633685561",
        "de": "applemusic://track/1633685561",
        "gb": "applemusic://track/1633685561",
        "fr": "applemusic://track/1633685561",
        "es": "applemusic://track/1633685561",
        "nl": "applemusic://track/1633685561",
        "it": "applemusic://track/1633685561"
      },
      "uri_youtube_music": "https://music.youtube.com/watch?v=K1FlAphL2p8",
      "uri_tidal": null,
      "uri_deezer": "deezer://track/99976952",
      "fun_fact": "A chart hit by Twenty One Pilots (2015).",
      "fun_fact_de": "Ein Chart-Hit von Twenty One Pilots (2015).",
      "fun_fact_es": "Un éxito de Twenty One Pilots (2015).",
      "fun_fact_fr": "Un tube de Twenty One Pilots (2015).",
      "fun_fact_nl": "Een chart-hit van Twenty One Pilots (2015)."
    },
    {
      "artist": "Clean Bandit",
      "title": "Solo (feat. Demi Lovato)",
      "year": 2018,
      "isrc": "GBAHS1800328",
      "uri": "spotify:track:6kPJZM97LwdG9QIsT7khp6",
      "uri_apple_music": "applemusic://track/1730098097",
      "uri_apple_music_by_region": {
        "us": "applemusic://track/1730098097",
        "de": "applemusic://track/1599296546",
        "gb": "applemusic://track/1750028478",
        "fr": "applemusic://track/1750028478",
        "es": "applemusic://track/1750028478",
        "nl": "applemusic://track/1675323822",
        "it": "applemusic://track/1750028478"
      },
      "uri_youtube_music": "https://music.youtube.com/watch?v=GvdKeZO8IzM",
      "uri_tidal": null,
      "uri_deezer": "deezer://track/497415082",
      "alt_artists": [
        "Demi Lovato"
      ],
      "fun_fact": "A chart hit by Clean Bandit (2018).",
      "fun_fact_de": "Ein Chart-Hit von Clean Bandit (2018).",
      "fun_fact_es": "Un éxito de Clean Bandit (2018).",
      "fun_fact_fr": "Un tube de Clean Bandit (2018).",
      "fun_fact_nl": "Een chart-hit van Clean Bandit (2018)."
    },
    {
      "artist": "Taylor Swift",
      "title": "Shake It Off",
      "year": 2015,
      "isrc": null,
      "uri": "spotify:track:0cqRj7pUJDkTCEsJkx8snD",
      "uri_apple_music": null,
      "uri_apple_music_by_region": {},
      "uri_youtube_music": "https://music.youtube.com/watch?v=sWMk8dwljFU",
      "uri_tidal": null,
      "uri_deezer": null,
      "fun_fact": "A chart hit by Taylor Swift (2015).",
      "fun_fact_de": "Ein Chart-Hit von Taylor Swift (2015).",
      "fun_fact_es": "Un éxito de Taylor Swift (2015).",
      "fun_fact_fr": "Un tube de Taylor Swift (2015).",
      "fun_fact_nl": "Een chart-hit van Taylor Swift (2015)."
    },
    {
      "artist": "Panic! At The Disco",
      "title": "High Hopes",
      "year": 2018,
      "isrc": "USAT21801174",
      "uri": "spotify:track:1rqqCSm0Qe4I9rUvWncaom",
      "uri_apple_music": "applemusic://track/1581587880",
      "uri_apple_music_by_region": {
        "us": "applemusic://track/1581587880",
        "de": "applemusic://track/1581587880",
        "gb": "applemusic://track/1581587880",
        "fr": "applemusic://track/1581587880",
        "es": "applemusic://track/1581587880",
        "nl": "applemusic://track/1581587880",
        "it": "applemusic://track/1581587880"
      },
      "uri_youtube_music": "https://music.youtube.com/watch?v=GJY8OMJXRAk",
      "uri_tidal": null,
      "uri_deezer": "deezer://track/516351532",
      "fun_fact": "A chart hit by Panic! At The Disco (2018).",
      "fun_fact_de": "Ein Chart-Hit von Panic! At The Disco (2018).",
      "fun_fact_es": "Un éxito de Panic! At The Disco (2018).",
      "fun_fact_fr": "Un tube de Panic! At The Disco (2018).",
      "fun_fact_nl": "Een chart-hit van Panic! At The Disco (2018)."
    },
    {
      "artist": "Taio Cruz",
      "title": "Dynamite",
      "year": 2010,
      "isrc": "GBUM71003721",
      "uri": "spotify:track:1DqdF42leyFIzqNDv9CjId",
      "uri_apple_music": "applemusic://track/1547314277",
      "uri_apple_music_by_region": {
        "us": "applemusic://track/1547314277",
        "de": "applemusic://track/1547314277",
        "gb": "applemusic://track/1547314277",
        "fr": "applemusic://track/1547314277",
        "es": "applemusic://track/1547314277",
        "nl": "applemusic://track/1547314277",
        "it": "applemusic://track/1547314277"
      },
      "uri_youtube_music": "https://music.youtube.com/watch?v=3MrY_BwLChk",
      "uri_tidal": null,
      "uri_deezer": "deezer://track/7063920",
      "fun_fact": "A chart hit by Taio Cruz (2010).",
      "fun_fact_de": "Ein Chart-Hit von Taio Cruz (2010).",
      "fun_fact_es": "Un éxito de Taio Cruz (2010).",
      "fun_fact_fr": "Un tube de Taio Cruz (2010).",
      "fun_fact_nl": "Een chart-hit van Taio Cruz (2010)."
    },
    {
      "artist": "Beyoncé",
      "title": "Run the World (Girls)",
      "year": 2011,
      "isrc": "USSM11102447",
      "uri": "spotify:track:1uXbwHHfgsXcUKfSZw5ZJ0",
      "uri_apple_music": "applemusic://track/626205874",
      "uri_apple_music_by_region": {
        "us": "applemusic://track/626205874",
        "de": "applemusic://track/626205874",
        "gb": "applemusic://track/626205874",
        "fr": "applemusic://track/626205874",
        "es": "applemusic://track/626205874",
        "nl": "applemusic://track/626205874",
        "it": "applemusic://track/626205874"
      },
      "uri_youtube_music": "https://music.youtube.com/watch?v=RnX3Qas9zCs",
      "uri_tidal": null,
      "uri_deezer": "deezer://track/10686934",
      "fun_fact": "A chart hit by Beyoncé (2011).",
      "fun_fact_de": "Ein Chart-Hit von Beyoncé (2011).",
      "fun_fact_es": "Un éxito de Beyoncé (2011).",
      "fun_fact_fr": "Un tube de Beyoncé (2011).",
      "fun_fact_nl": "Een chart-hit van Beyoncé (2011)."
    },
    {
      "artist": "Avicii",
      "title": "Waiting For Love",
      "year": 2015,
      "isrc": "CHB701400134",
      "uri": "spotify:track:2P4OICZRVAQcYAV2JReRfj",
      "uri_apple_music": "applemusic://track/1807714122",
      "uri_apple_music_by_region": {
        "us": "applemusic://track/1807714122",
        "de": "applemusic://track/1807714122",
        "gb": "applemusic://track/1807714122",
        "fr": "applemusic://track/1807714122",
        "es": "applemusic://track/1442321813",
        "nl": "applemusic://track/1807714122",
        "it": "applemusic://track/1807714122"
      },
      "uri_youtube_music": "https://music.youtube.com/watch?v=iR1sAex__VA",
      "uri_tidal": null,
      "uri_deezer": "deezer://track/107346368",
      "fun_fact": "A chart hit by Avicii (2015).",
      "fun_fact_de": "Ein Chart-Hit von Avicii (2015).",
      "fun_fact_es": "Un éxito de Avicii (2015).",
      "fun_fact_fr": "Un tube de Avicii (2015).",
      "fun_fact_nl": "Een chart-hit van Avicii (2015)."
    },
    {
      "artist": "P!nk",
      "title": "Raise Your Glass",
      "year": 2010,
      "isrc": "USLF21000090",
      "uri": "spotify:track:1gv4xPanImH17bKZ9rOveR",
      "uri_apple_music": "applemusic://track/1625989507",
      "uri_apple_music_by_region": {
        "us": "applemusic://track/1625989507",
        "de": "applemusic://track/1625989507",
        "gb": "applemusic://track/1625989507",
        "fr": "applemusic://track/1625989507",
        "es": "applemusic://track/1625989507",
        "nl": "applemusic://track/1625989507",
        "it": "applemusic://track/1625989507"
      },
      "uri_youtube_music": "https://music.youtube.com/watch?v=Ch_NfEOxzh4",
      "uri_tidal": null,
      "uri_deezer": "deezer://track/15597831",
      "fun_fact": "A chart hit by P!nk (2010).",
      "fun_fact_de": "Ein Chart-Hit von P!nk (2010).",
      "fun_fact_es": "Un éxito de P!nk (2010).",
      "fun_fact_fr": "Un tube de P!nk (2010).",
      "fun_fact_nl": "Een chart-hit van P!nk (2010)."
    },
    {
      "artist": "AronChupa",
      "title": "I'm an Albatraoz",
      "year": 2014,
      "isrc": "SEYOK1406001",
      "uri": "spotify:track:5XSSGkeN6FJm7AAowBCLEW",
      "uri_apple_music": "applemusic://track/907071271",
      "uri_apple_music_by_region": {
        "us": "applemusic://track/907071271",
        "de": "applemusic://track/1001571199",
        "gb": "applemusic://track/907071271",
        "fr": "applemusic://track/907071271",
        "es": "applemusic://track/907071271",
        "nl": "applemusic://track/907071271",
        "it": "applemusic://track/907071271"
      },
      "uri_youtube_music": "https://music.youtube.com/watch?v=cbHs1Mx2M6Y",
      "uri_tidal": null,
      "uri_deezer": "deezer://track/82564724",
      "fun_fact": "A chart hit by AronChupa (2014).",
      "fun_fact_de": "Ein Chart-Hit von AronChupa (2014).",
      "fun_fact_es": "Un éxito de AronChupa (2014).",
      "fun_fact_fr": "Un tube de AronChupa (2014).",
      "fun_fact_nl": "Een chart-hit van AronChupa (2014)."
    },
    {
      "artist": "ROSÉ",
      "title": "APT.",
      "year": 2024,
      "isrc": "USAT22409172",
      "uri": "spotify:track:5vNRhkKd0yEAg8suGBpjeY",
      "uri_apple_music": "applemusic://track/1820145146",
      "uri_apple_music_by_region": {
        "us": "applemusic://track/1820145146",
        "de": "applemusic://track/1843357607",
        "gb": "applemusic://track/1820145146",
        "fr": "applemusic://track/1820145146",
        "es": "applemusic://track/1820145146",
        "nl": "applemusic://track/1820145146",
        "it": "applemusic://track/1820145146"
      },
      "uri_youtube_music": "https://music.youtube.com/watch?v=DiTd771WumE",
      "uri_tidal": null,
      "uri_deezer": "deezer://track/3050380851",
      "alt_artists": [
        "Bruno Mars"
      ],
      "fun_fact": "A chart hit by ROSÉ (2024).",
      "fun_fact_de": "Ein Chart-Hit von ROSÉ (2024).",
      "fun_fact_es": "Un éxito de ROSÉ (2024).",
      "fun_fact_fr": "Un tube de ROSÉ (2024).",
      "fun_fact_nl": "Een chart-hit van ROSÉ (2024)."
    },
    {
      "artist": "Vincent Gross",
      "title": "Ouzo",
      "year": 2023,
      "isrc": "CH7812354719",
      "uri": "spotify:track:6QeQs7lz8qR2miwx9n2epp",
      "uri_apple_music": "applemusic://track/1862841058",
      "uri_apple_music_by_region": {
        "us": "applemusic://track/1862841058",
        "de": "applemusic://track/1862841058",
        "gb": "applemusic://track/1862841058",
        "fr": "applemusic://track/1862841058",
        "es": "applemusic://track/1862841058",
        "nl": "applemusic://track/1862841058",
        "it": "applemusic://track/1705233750"
      },
      "uri_youtube_music": "https://music.youtube.com/watch?v=bKoWnKMgRr8",
      "uri_tidal": null,
      "uri_deezer": "deezer://track/2434257815",
      "fun_fact": "A chart hit by Vincent Gross (2023).",
      "fun_fact_de": "Ein Chart-Hit von Vincent Gross (2023).",
      "fun_fact_es": "Un éxito de Vincent Gross (2023).",
      "fun_fact_fr": "Un tube de Vincent Gross (2023).",
      "fun_fact_nl": "Een chart-hit van Vincent Gross (2023)."
    },
    {
      "artist": "AFROJACK",
      "title": "Hero",
      "year": 2021,
      "isrc": "CYA222100011",
      "uri": "spotify:track:29p6UW08MXzwj9thWBW3uF",
      "uri_apple_music": "applemusic://track/1561995397",
      "uri_apple_music_by_region": {
        "us": "applemusic://track/1561995397",
        "de": "applemusic://track/1561995397",
        "gb": "applemusic://track/1561995397",
        "fr": "applemusic://track/1561995397",
        "es": "applemusic://track/1561995397",
        "nl": "applemusic://track/1591459330",
        "it": "applemusic://track/1561995397"
      },
      "uri_youtube_music": "https://music.youtube.com/watch?v=k8j-4Kk49kA",
      "uri_tidal": null,
      "uri_deezer": "deezer://track/1327838722",
      "alt_artists": [
        "David Guetta"
      ],
      "fun_fact": "A chart hit by AFROJACK (2021).",
      "fun_fact_de": "Ein Chart-Hit von AFROJACK (2021).",
      "fun_fact_es": "Un éxito de AFROJACK (2021).",
      "fun_fact_fr": "Un tube de AFROJACK (2021).",
      "fun_fact_nl": "Een chart-hit van AFROJACK (2021)."
    },
    {
      "artist": "Cascada",
      "title": "Because the Night",
      "year": 2010,
      "isrc": "DEHK90780401",
      "uri": "spotify:track:0dLMK9i5dLoYYrGXFdlcT3",
      "uri_apple_music": "applemusic://track/522361255",
      "uri_apple_music_by_region": {
        "us": "applemusic://track/522361255",
        "de": "applemusic://track/522361255",
        "gb": "applemusic://track/522361255",
        "fr": "applemusic://track/522361255",
        "es": "applemusic://track/522361255",
        "nl": "applemusic://track/522361255",
        "it": "applemusic://track/522361255"
      },
      "uri_youtube_music": "https://music.youtube.com/watch?v=p0nOjNyoMik",
      "uri_tidal": null,
      "uri_deezer": "deezer://track/5477458",
      "fun_fact": "A chart hit by Cascada (2010).",
      "fun_fact_de": "Ein Chart-Hit von Cascada (2010).",
      "fun_fact_es": "Un éxito de Cascada (2010).",
      "fun_fact_fr": "Un tube de Cascada (2010).",
      "fun_fact_nl": "Een chart-hit van Cascada (2010)."
    },
    {
      "artist": "OneRepublic",
      "title": "I Ain't Worried",
      "year": 2022,
      "isrc": "USUM72206227",
      "uri": "spotify:track:4h9wh7iOZ0GGn8QVp4RAOB",
      "uri_apple_music": "applemusic://track/1708513411",
      "uri_apple_music_by_region": {
        "us": "applemusic://track/1708513411",
        "de": "applemusic://track/1708513411",
        "gb": "applemusic://track/1708513411",
        "fr": "applemusic://track/1708513411",
        "es": "applemusic://track/1708513411",
        "nl": "applemusic://track/1693890843",
        "it": "applemusic://track/1708513411"
      },
      "uri_youtube_music": "https://music.youtube.com/watch?v=-K9VwBEOI-Q",
      "uri_tidal": null,
      "uri_deezer": "deezer://track/1764283667",
      "fun_fact": "A chart hit by OneRepublic (2022).",
      "fun_fact_de": "Ein Chart-Hit von OneRepublic (2022).",
      "fun_fact_es": "Un éxito de OneRepublic (2022).",
      "fun_fact_fr": "Un tube de OneRepublic (2022).",
      "fun_fact_nl": "Een chart-hit van OneRepublic (2022)."
    },
    {
      "artist": "Chris Brown",
      "title": "Yeah 3x",
      "year": 2011,
      "isrc": "USJI11000230",
      "uri": "spotify:track:2QtxlzvSBONjs1bDC34ixs",
      "uri_apple_music": "applemusic://track/422045127",
      "uri_apple_music_by_region": {
        "us": "applemusic://track/422045127",
        "de": "applemusic://track/904436694",
        "gb": "applemusic://track/581006852",
        "fr": "applemusic://track/858595853",
        "es": "applemusic://track/581006852",
        "nl": "applemusic://track/904436694",
        "it": "applemusic://track/581006852"
      },
      "uri_youtube_music": "https://music.youtube.com/watch?v=fmYLvHnh8bQ",
      "uri_tidal": null,
      "uri_deezer": "deezer://track/652442562",
      "fun_fact": "A chart hit by Chris Brown (2011).",
      "fun_fact_de": "Ein Chart-Hit von Chris Brown (2011).",
      "fun_fact_es": "Un éxito de Chris Brown (2011).",
      "fun_fact_fr": "Un tube de Chris Brown (2011).",
      "fun_fact_nl": "Een chart-hit van Chris Brown (2011)."
    },
    {
      "artist": "Miley Cyrus",
      "title": "Midnight Sky",
      "year": 2020,
      "isrc": "USRC12002653",
      "uri": "spotify:track:4i2qxFEVVUi8yOYoxB8TCX",
      "uri_apple_music": "applemusic://track/1625999816",
      "uri_apple_music_by_region": {
        "us": "applemusic://track/1625999816",
        "de": "applemusic://track/1625999816",
        "gb": "applemusic://track/1625999816",
        "fr": "applemusic://track/1625999816",
        "es": "applemusic://track/1625999816",
        "nl": "applemusic://track/1625999816",
        "it": "applemusic://track/1625999816"
      },
      "uri_youtube_music": "https://music.youtube.com/watch?v=ytiqx4Qrias",
      "uri_tidal": null,
      "uri_deezer": "deezer://track/1151534142",
      "fun_fact": "A chart hit by Miley Cyrus (2020).",
      "fun_fact_de": "Ein Chart-Hit von Miley Cyrus (2020).",
      "fun_fact_es": "Un éxito de Miley Cyrus (2020).",
      "fun_fact_fr": "Un tube de Miley Cyrus (2020).",
      "fun_fact_nl": "Een chart-hit van Miley Cyrus (2020)."
    },
    {
      "artist": "Nicky Jam",
      "title": "El Perdón (with Enrique Iglesias)",
      "year": 2017,
      "isrc": "USSD11500005",
      "uri": "spotify:track:7qCAVkHWZkF44OzOUKf8Cr",
      "uri_apple_music": "applemusic://track/1585690495",
      "uri_apple_music_by_region": {
        "us": "applemusic://track/1585690495",
        "de": "applemusic://track/1585690495",
        "gb": "applemusic://track/1585690495",
        "fr": "applemusic://track/1585690495",
        "es": "applemusic://track/1585690495",
        "nl": "applemusic://track/1757602520",
        "it": "applemusic://track/1585690495"
      },
      "uri_youtube_music": "https://music.youtube.com/watch?v=zs6aDvOTlMo",
      "uri_tidal": null,
      "uri_deezer": "deezer://track/140421809",
      "alt_artists": [
        "Enrique Iglesias"
      ],
      "fun_fact": "A chart hit by Nicky Jam (2017).",
      "fun_fact_de": "Ein Chart-Hit von Nicky Jam (2017).",
      "fun_fact_es": "Un éxito de Nicky Jam (2017).",
      "fun_fact_fr": "Un tube de Nicky Jam (2017).",
      "fun_fact_nl": "Een chart-hit van Nicky Jam (2017)."
    },
    {
      "artist": "USHER",
      "title": "More - RedOne Jimmy Joker Remix",
      "year": 2011,
      "isrc": "USLF21000098",
      "uri": "spotify:track:0aBKFfdyOD1Ttvgv0cfjjJ",
      "uri_apple_music": "applemusic://track/408922516",
      "uri_apple_music_by_region": {
        "us": "applemusic://track/408922516",
        "de": "applemusic://track/1308507616",
        "gb": "applemusic://track/581006860",
        "fr": "applemusic://track/1308507616",
        "es": "applemusic://track/581006860",
        "nl": "applemusic://track/1308507616",
        "it": "applemusic://track/581006860"
      },
      "uri_youtube_music": "https://music.youtube.com/watch?v=yeNkkBof_Nc",
      "uri_tidal": null,
      "uri_deezer": "deezer://track/9793266",
      "fun_fact": "A chart hit by USHER (2011).",
      "fun_fact_de": "Ein Chart-Hit von USHER (2011).",
      "fun_fact_es": "Un éxito de USHER (2011).",
      "fun_fact_fr": "Un tube de USHER (2011).",
      "fun_fact_nl": "Een chart-hit van USHER (2011)."
    },
    {
      "artist": "SIRA",
      "title": "9 bis 9",
      "year": 2023,
      "isrc": "DEKF22300419",
      "uri": "spotify:track:5YWu6dt50Nieq8qi572RF8",
      "uri_apple_music": "applemusic://track/1684143909",
      "uri_apple_music_by_region": {
        "us": "applemusic://track/1684143909",
        "de": "applemusic://track/1684143909",
        "gb": "applemusic://track/1684143909",
        "fr": "applemusic://track/1684143909",
        "es": "applemusic://track/1684143909",
        "nl": "applemusic://track/1684143909",
        "it": "applemusic://track/1684143909"
      },
      "uri_youtube_music": "https://music.youtube.com/watch?v=6KySepYfaOE",
      "uri_tidal": null,
      "uri_deezer": "deezer://track/2251899577",
      "alt_artists": [
        "Bausa",
        "badchieff"
      ],
      "fun_fact": "A chart hit by SIRA (2023).",
      "fun_fact_de": "Ein Chart-Hit von SIRA (2023).",
      "fun_fact_es": "Un éxito de SIRA (2023).",
      "fun_fact_fr": "Un tube de SIRA (2023).",
      "fun_fact_nl": "Een chart-hit van SIRA (2023)."
    },
    {
      "artist": "Olivia Rodrigo",
      "title": "good 4 u",
      "year": 2021,
      "isrc": "USUG12101245",
      "uri": "spotify:track:4ZtFanR9U6ndgddUvNcjcG",
      "uri_apple_music": "applemusic://track/1610192322",
      "uri_apple_music_by_region": {
        "us": "applemusic://track/1610192322",
        "de": "applemusic://track/1610192322",
        "gb": "applemusic://track/1610192322",
        "fr": "applemusic://track/1610192322",
        "es": "applemusic://track/1610192322",
        "nl": "applemusic://track/1610192322",
        "it": "applemusic://track/1610192322"
      },
      "uri_youtube_music": "https://music.youtube.com/watch?v=Bc9ijogGmtU",
      "uri_tidal": null,
      "uri_deezer": "deezer://track/1378342622",
      "fun_fact": "A chart hit by Olivia Rodrigo (2021).",
      "fun_fact_de": "Ein Chart-Hit von Olivia Rodrigo (2021).",
      "fun_fact_es": "Un éxito de Olivia Rodrigo (2021).",
      "fun_fact_fr": "Un tube de Olivia Rodrigo (2021).",
      "fun_fact_nl": "Een chart-hit van Olivia Rodrigo (2021)."
    },
    {
      "artist": "Alvaro Soler",
      "title": "Solo Para Ti",
      "year": 2022,
      "isrc": "DEUM72201943",
      "uri": "spotify:track:2uAgZ0PelSImQe3BME9CiT",
      "uri_apple_music": "applemusic://track/1687407045",
      "uri_apple_music_by_region": {
        "us": "applemusic://track/1687407045",
        "de": "applemusic://track/1687407045",
        "gb": "applemusic://track/1687407045",
        "fr": "applemusic://track/1687407045",
        "es": "applemusic://track/1687407045",
        "nl": "applemusic://track/1687407045",
        "it": "applemusic://track/1687407045"
      },
      "uri_youtube_music": "https://music.youtube.com/watch?v=lPX_POCmlT0",
      "uri_tidal": null,
      "uri_deezer": "deezer://track/1721704657",
      "alt_artists": [
        "Topic"
      ],
      "fun_fact": "A chart hit by Alvaro Soler (2022).",
      "fun_fact_de": "Ein Chart-Hit von Alvaro Soler (2022).",
      "fun_fact_es": "Un éxito de Alvaro Soler (2022).",
      "fun_fact_fr": "Un tube de Alvaro Soler (2022).",
      "fun_fact_nl": "Een chart-hit van Alvaro Soler (2022)."
    },
    {
      "artist": "PSY",
      "title": "Gangnam Style (강남스타일)",
      "year": 2012,
      "isrc": "USUM71210283",
      "uri": "spotify:track:03UrZgTINDqvnUMbbIMhql",
      "uri_apple_music": "applemusic://track/1698452617",
      "uri_apple_music_by_region": {
        "us": "applemusic://track/1698452617",
        "de": "applemusic://track/1698452617",
        "gb": "applemusic://track/1698452617",
        "fr": "applemusic://track/1698452617",
        "es": "applemusic://track/1698452617",
        "nl": "applemusic://track/1698452617",
        "it": "applemusic://track/1698452617"
      },
      "uri_youtube_music": "https://music.youtube.com/watch?v=4AgDYTuZWOw",
      "uri_tidal": null,
      "uri_deezer": "deezer://track/60726278",
      "fun_fact": "A chart hit by PSY (2012).",
      "fun_fact_de": "Ein Chart-Hit von PSY (2012).",
      "fun_fact_es": "Un éxito de PSY (2012).",
      "fun_fact_fr": "Un tube de PSY (2012).",
      "fun_fact_nl": "Een chart-hit van PSY (2012)."
    },
    {
      "artist": "Axwell /\\ Ingrosso",
      "title": "Sun Is Shining",
      "year": 2017,
      "isrc": "USUG11500070",
      "uri": "spotify:track:4b2tcjrG1qUkSdsqEFP2dB",
      "uri_apple_music": "applemusic://track/1440907562",
      "uri_apple_music_by_region": {
        "us": "applemusic://track/1440907562",
        "de": "applemusic://track/1440907562",
        "gb": "applemusic://track/1440907562",
        "fr": "applemusic://track/1440907562",
        "es": "applemusic://track/1440907562",
        "nl": "applemusic://track/1443050882",
        "it": "applemusic://track/1440907562"
      },
      "uri_youtube_music": "https://music.youtube.com/watch?v=7e-A7y9WesI",
      "uri_tidal": null,
      "uri_deezer": "deezer://track/437979092",
      "alt_artists": [
        "Axwell",
        "Sebastian Ingrosso"
      ],
      "fun_fact": "A chart hit by Axwell /\\ Ingrosso (2017).",
      "fun_fact_de": "Ein Chart-Hit von Axwell /\\ Ingrosso (2017).",
      "fun_fact_es": "Un éxito de Axwell /\\ Ingrosso (2017).",
      "fun_fact_fr": "Un tube de Axwell /\\ Ingrosso (2017).",
      "fun_fact_nl": "Een chart-hit van Axwell /\\ Ingrosso (2017)."
    },
    {
      "artist": "Nathan Evans",
      "title": "Wellerman - Sea Shanty",
      "year": 2021,
      "isrc": "GBUM72100297",
      "uri": "spotify:track:54OBgO0Xwu20Jak9TMXbR7",
      "uri_apple_music": "applemusic://track/1686851816",
      "uri_apple_music_by_region": {
        "us": "applemusic://track/1686851816",
        "de": "applemusic://track/1686851816",
        "gb": "applemusic://track/1686851816",
        "fr": "applemusic://track/1686851816",
        "es": "applemusic://track/1686851816",
        "nl": "applemusic://track/1686851816",
        "it": "applemusic://track/1686851816"
      },
      "uri_youtube_music": "https://music.youtube.com/watch?v=D458Eaql_aQ",
      "uri_tidal": null,
      "uri_deezer": "deezer://track/1217037082",
      "fun_fact": "A chart hit by Nathan Evans (2021).",
      "fun_fact_de": "Ein Chart-Hit von Nathan Evans (2021).",
      "fun_fact_es": "Un éxito de Nathan Evans (2021).",
      "fun_fact_fr": "Un tube de Nathan Evans (2021).",
      "fun_fact_nl": "Een chart-hit van Nathan Evans (2021)."
    },
    {
      "artist": "Mark Ronson",
      "title": "Uptown Funk (feat. Bruno Mars)",
      "year": 2015,
      "isrc": "GBARL1401524",
      "uri": "spotify:track:32OlwWuMpZ6b0aN2RZOeMS",
      "uri_apple_music": "applemusic://track/1696304502",
      "uri_apple_music_by_region": {
        "us": "applemusic://track/1696304502",
        "de": "applemusic://track/1696304502",
        "gb": "applemusic://track/1696304502",
        "fr": "applemusic://track/1696304502",
        "es": "applemusic://track/1696304502",
        "nl": "applemusic://track/1696304502",
        "it": "applemusic://track/1696304502"
      },
      "uri_youtube_music": "https://music.youtube.com/watch?v=tYvFa2ARD24",
      "uri_tidal": null,
      "uri_deezer": "deezer://track/92734438",
      "alt_artists": [
        "Bruno Mars"
      ],
      "fun_fact": "A chart hit by Mark Ronson (2015).",
      "fun_fact_de": "Ein Chart-Hit von Mark Ronson (2015).",
      "fun_fact_es": "Un éxito de Mark Ronson (2015).",
      "fun_fact_fr": "Un tube de Mark Ronson (2015).",
      "fun_fact_nl": "Een chart-hit van Mark Ronson (2015)."
    },
    {
      "artist": "Daft Punk",
      "title": "Get Lucky (Radio Edit) [feat. Pharrell Williams and Nile Rodgers]",
      "year": 2013,
      "isrc": null,
      "uri": "spotify:track:2Foc5Q5nqNiosCNqttzHof",
      "uri_apple_music": null,
      "uri_apple_music_by_region": {},
      "uri_youtube_music": "https://music.youtube.com/watch?v=Rgrt_8mXrK8",
      "uri_tidal": null,
      "uri_deezer": null,
      "alt_artists": [
        "Pharrell Williams",
        "Nile Rodgers"
      ],
      "fun_fact": "A chart hit by Daft Punk (2013).",
      "fun_fact_de": "Ein Chart-Hit von Daft Punk (2013).",
      "fun_fact_es": "Un éxito de Daft Punk (2013).",
      "fun_fact_fr": "Un tube de Daft Punk (2013).",
      "fun_fact_nl": "Een chart-hit van Daft Punk (2013)."
    },
    {
      "year": 2010,
      "uri": "spotify:track:7w87IxuO7BDcJ3YUqCyMTT",
      "artist": "Foster The People",
      "alt_artists": [
        "MGMT",
        "Passion Pit",
        "Two Door Cinema Club",
        "Walk the Moon"
      ],
      "title": "Pumped Up Kicks",
      "chart_info": {
        "billboard_peak": 3,
        "uk_peak": 18,
        "weeks_on_chart": 37
      },
      "certifications": [
        "6x Platinum (US)"
      ],
      "awards": [],
      "fun_fact": "⚠️ NOTE: Released in 2010, technically outside the 2000-2009 range. The song's dark lyrics about a troubled youth are contrasted by its upbeat indie-pop melody.",
      "fun_fact_de": "⚠️ HINWEIS: 2010 veröffentlicht, technisch außerhalb des 2000-2009-Zeitraums. Die dunklen Texte über einen gestörten Jugendlichen stehen im Kontrast zur fröhlichen Indie-Pop-Melodie.",
      "fun_fact_es": "⚠️ NOTA: Lanzada en 2010, técnicamente fuera del rango 2000-2009. La letra oscura sobre un joven problemático contrasta con su alegre melodía indie-pop.",
      "fun_fact_fr": "Sorti en 2010, donc techniquement hors de la période 2000-2009. Les paroles sombres sur un jeune en difficulté contrastent avec la mélodie indie-pop entraînante du titre.",
      "uri_apple_music": "applemusic://track/435761212",
      "uri_youtube_music": "https://music.youtube.com/watch?v=SDTZ7iX4vTQ",
      "uri_tidal": "tidal://track/25280917",
      "uri_deezer": "deezer://track/15546830",
      "fun_fact_nl": "⚠️ OPMERKING: Uitgebracht in 2010, technisch gezien buiten het bereik 2000-2009. de duistere tekst van het nummer over een probleemjongere wordt gecontrasteerd door de vrolijke indie-popmelodie.",
      "awards_nl": [],
      "isrc": "USSM11002931",
      "uri_apple_music_by_region": {
        "us": "applemusic://track/1459540500",
        "de": "applemusic://track/1459540500",
        "gb": "applemusic://track/1459540500",
        "fr": "applemusic://track/1459540500",
        "es": "applemusic://track/1459540500",
        "nl": "applemusic://track/1459540500",
        "it": "applemusic://track/1459540500"
      }
    },
    {
      "year": 2015,
      "uri": "spotify:track:3iVcZ5G6tvkXZkZKlMpIUs",
      "artist": "Kendrick Lamar",
      "alt_artists": [
        "J. Cole",
        "Chance The Rapper",
        "Childish Gambino",
        "Tyler, The Creator"
      ],
      "title": "Alright",
      "chart_info": {
        "billboard_peak": 57,
        "uk_peak": 81,
        "weeks_on_chart": 12
      },
      "certifications": [
        "3x Platinum (US)"
      ],
      "awards": [],
      "fun_fact": "Though from 2015 (outside the 2000s decade), Alright became an anthem of the Black Lives Matter movement. Produced by Pharrell Williams, its chant 'We gon' be alright' was adopted at protests across America.",
      "fun_fact_de": "Obwohl der Song aus dem Jahr 2015 stammt, wurde 'Alright' zur Hymne der Black-Lives-Matter-Bewegung. Von Pharrell Williams produziert, wurde der Refrain 'We gon' be alright' bei Protesten in ganz Amerika gesungen.",
      "fun_fact_es": "Aunque es de 2015 (fuera de la década de los 2000), 'Alright' se convirtió en el himno del movimiento Black Lives Matter. Producida por Pharrell Williams, su coro fue adoptado en protestas por toda América.",
      "fun_fact_fr": "Bien que sortie en 2015 (hors de la décennie 2000), Alright est devenue un hymne du mouvement Black Lives Matter. Produite par Pharrell Williams, son refrain 'We gon' be alright' a été repris lors de manifestations à travers les États-Unis.",
      "uri_apple_music": "applemusic://track/1440829463",
      "uri_youtube_music": "https://music.youtube.com/watch?v=Z-48u_uWMHY",
      "uri_tidal": "tidal://track/77703643",
      "uri_deezer": "deezer://track/97206068",
      "fun_fact_nl": "Hoewel uit 2015 (buiten het jaren 2000-decennium), werd Alright een volkslied van de Black Lives Matter-beweging. Geproduceerd door Pharrell Williams, werd de chant 'We gon' be alright' overgenomen bij protesten in heel Amerika.",
      "awards_nl": [],
      "isrc": "USUM71502498",
      "uri_apple_music_by_region": {
        "us": "applemusic://track/1440829463",
        "de": "applemusic://track/1440829463",
        "gb": "applemusic://track/1440829463",
        "fr": "applemusic://track/1440829463",
        "es": "applemusic://track/1440829463",
        "nl": "applemusic://track/1440829463",
        "it": "applemusic://track/1440829463"
      }
    },
    {
      "year": 2010,
      "uri": "spotify:track:2V4bv1fNWfTcyRJKmej6Sj",
      "artist": "Mike Posner",
      "alt_artists": [
        "B.o.B",
        "Jason Derulo",
        "Travie McCoy",
        "Gym Class Heroes"
      ],
      "title": "Cooler Than Me",
      "chart_info": {
        "billboard_peak": 6,
        "uk_peak": 5,
        "weeks_on_chart": 22
      },
      "certifications": [
        "4x Platinum (US)",
        "Silver (UK)"
      ],
      "awards": [],
      "fun_fact": "Though from 2010 (just outside the 2000s), Mike Posner wrote and produced this song in his dorm room at Duke University. The remix by Gigamesh turned it from a blog hit into a worldwide smash.",
      "fun_fact_de": "Obwohl von 2010 (knapp außerhalb der 2000er), schrieb und produzierte Mike Posner den Song in seinem Studentenwohnheim an der Duke University. Der Gigamesh-Remix verwandelte ihn von einem Blog-Hit in einen weltweiten Erfolg.",
      "fun_fact_es": "Aunque es de 2010, Mike Posner escribió y produjo esta canción en su dormitorio de la Universidad Duke. El remix de Gigamesh la transformó de un éxito de blogs a un hit mundial.",
      "fun_fact_fr": "Bien que sorti en 2010 (juste en dehors des années 2000), Mike Posner a écrit et produit ce titre dans sa chambre d'étudiant à l'université Duke. Le remix de Gigamesh l'a transformé d'un tube de blogs en succès planétaire.",
      "uri_apple_music": "applemusic://track/383458635",
      "uri_youtube_music": "https://music.youtube.com/watch?v=Bsr8hb3TPBI",
      "uri_tidal": "tidal://track/4253935",
      "uri_deezer": "deezer://track/6697128",
      "fun_fact_nl": "Hoewel uit 2010 (vlak buiten de jaren 2000), schreef en produceerde Mike Posner dit nummer in zijn studentenkamer aan de Duke University. De remix door Gigamesh maakte er van een bloghit een wereldwijde knaller van.",
      "awards_nl": [],
      "isrc": "USJAY1000035",
      "uri_apple_music_by_region": {
        "us": "applemusic://track/1744523906",
        "de": "applemusic://track/1744523906",
        "gb": "applemusic://track/1744523906",
        "fr": "applemusic://track/1744523906",
        "es": "applemusic://track/1744523906",
        "nl": "applemusic://track/1744523906",
        "it": "applemusic://track/1744523906"
      }
    }
  ]
}
